Workbook
Name Slicer_Clean_Date__Year: #N/A
Name Slicer_Product_Category: #N/A
Name Slicer_Region: #N/A

Sheet Dashboard

Sheet Region Wise Sales Analysis
A3: Row Labels | B3: Average of Clean_Sales
A4: CENTRAL | B4: 1258.8078
A5: EAST | B5: 1219.332
A6: NORTH | B6: 1246.6992
A7: SOUTH | B7: 1213.8751
A8: WEST | B8: 1246.2482
A9: Grand Total | B9: 1238.3779

Sheet Product Category Performance
A3: Row Labels | B3: Sum of Clean_Sales
A4: Electronics | B4: 3270619.6
A5: Furniture | B5: 1428950.9
A6: Office Supplies | B6: 1492318.9
A7: Grand Total | B7: 6191889.4

Sheet Monthly Sales Trend
A3: Row Labels | B3: Sum of Clean_Sales
A4: Jan | B4: 653663.49
A5: Feb | B5: 561058.56
A6: Mar | B6: 661979.52
A7: Apr | B7: 743810.91
A8: May | B8: 547740.51
A9: Jun | B9: 454813.31
A10: Jul | B10: 454415.86
A11: Aug | B11: 468583.93
A12: Sep | B12: 439960.37
A13: Oct | B13: 383109.08
A14: Nov | B14: 413740.6
A15: Dec | B15: 409013.25
A16: Grand Total | B16: 6191889.4

Sheet Department Salary Summary
A3: Row Labels | B3: Sum of Clean_Salary
A4: Finance | B4: 5224381
A5: HR | B5: 5594342
A6: IT | B6: 6331284
A7: Operations | B7: 5465744
A8: Sales | B8: 13430554
A9: Grand Total | B9: 36046305

Sheet Delivery Performance
A3: Row Labels | B3: Count of Shipment_ID
A4: Delayed | B4: 694
A5: Lost | B5: 630
A6: On Time | B6: 676
A7: Grand Total | B7: 2000

Sheet Return Analysis
A3: Row Labels | B3: Count of Return_ID
A4: Customer Changed Mind | B4: 141
A5: Damaged | B5: 144
A6: Late Delivery | B6: 157
A7: Wrong Item | B7: 158
A8: Grand Total | B8: 600

Sheet Inventory Stock Analysis
A1: Warehouse | B1: All
A3: Row Labels | B3: Count of Stock_Qty
A4: Also | B4: 3
A5: Argue | B5: 3
A6: Catch | B6: 3
A7: Character | B7: 3
A8: Cost | B8: 3
A9: Course | B9: 3
A10: Crime | B10: 3
A11: Cultural | B11: 3
A12: Hour | B12: 4
A13: Reveal | B13: 4
A14: Grand Total | B14: 32

Sheet Supplier Performance
A3: Row Labels | B3: Sum of Rating
A4: Greer, Holland and Hess | B4: 4.8
A5: Howell-George | B5: 4.7
A6: Mcintyre-Carter | B6: 5
A7: Moore-Gutierrez | B7: 4.8
A8: Steele, Wright and Martinez | B8: 5
A9: Grand Total | B9: 24.3

Sheet Shipment Cost Analysis
A3: Row Labels | B3: Average of Transport_Cost
A4: DHL | B4: 5088.5774
A5: FedEx | B5: 4923.9507
A6: TCS | B6: 4983.4737
A7: UPS | B7: 5085.7049
A8: Grand Total | B8: 5019.833

Sheet Orders
A1: Order_ID | B1: Clean_ID | C1: Customer_Name | D1: Clean_Name | E1: Region | F1: Clean_Region | G1: Product_Category | H1: Clean_Product | I1: Order_Date | J1: Clean_Date | K1: Sales_Amount | L1: Clean_Sales | M1: Sales_Classification | N1: Sales_Grade | O1: Discount_% | P1: Clean_Discount | Q1: Status | R1: Delivery_Days | S1: Custom_Shipping_Label | T1: Total Sales | V1: =SUM(L2:L5001) -> 6191889.4
A2: ORD1000 | B2: =RIGHT(A2, 4) -> 1000 | C2: Tony Gibbs | D2: =PROPER(TRIM(C2)) -> Tony Gibbs | E2: north | F2: =UPPER(TRIM(E2)) -> NORTH | G2: Electronics | H2: =PROPER(TRIM(G2)) -> Electronics | I2: 01-26-2024 | J2: 45317 | K2: 1411.4 | L2: 1411.4 | M2: =IF(L2>2500, "High Sales", "Low Sales") -> Low Sales | N2: =IF(OR(ISBLANK(L2), L2="", L2=0), "Grade C", IF(L2>=4000, "Grade A", IF(L2>=2000, "Grade B", "Grade C"))) -> Grade C | O2: 10 | P2: 10 | Q2: Delivered | R2: 11 | S2: =CONCATENATE(OrdersTable[[#This Row],[Clean_ID]],"-",OrdersTable[[#This Row],[Clean_Region]],"-",OrdersTable[[#This Row],[Clean_Product]]) -> 1000-NORTH-Electronics | T2: Regional Sales (north) | V2: =SUMIF(Orders!E:E, "North", Orders!K:K) -> 2040846.6
A3: ORD1001 | B3: =RIGHT(A3, 4) -> 1001 | C3: April Pacheco | D3: =PROPER(TRIM(C3)) -> April Pacheco | E3: north | F3: =UPPER(TRIM(E3)) -> NORTH | G3: Electronics | H3: =PROPER(TRIM(G3)) -> Electronics | I3: 27/08/2025 | J3: 45896 | K3: 207.32 | L3: 207.32 | M3: =IF(L3>2500, "High Sales", "Low Sales") -> Low Sales | N3: =IF(OR(ISBLANK(L3), L3="", L3=0), "Grade C", IF(L3>=4000, "Grade A", IF(L3>=2000, "Grade B", "Grade C"))) -> Grade C | O3: 10 | P3: 10 | Q3: Pending | R3: 9 | S3: =CONCATENATE(OrdersTable[[#This Row],[Clean_ID]],"-",OrdersTable[[#This Row],[Clean_Region]],"-",OrdersTable[[#This Row],[Clean_Product]]) -> 1001-NORTH-Electronics | T3: Category Performance(electronic sales in north) | V3: =SUMIFS(Orders!K:K, Orders!F:F, "NORTH", Orders!H:H, "Electronics") -> 1078393.2
A4: ORD1002 | B4: =RIGHT(A4, 4) -> 1002 | C4: Patrick Leon | D4: =PROPER(TRIM(C4)) -> Patrick Leon | E4: Central | F4: =UPPER(TRIM(E4)) -> CENTRAL | G4: Electronics | H4: =PROPER(TRIM(G4)) -> Electronics | I4: 2025-07-28 | J4: 45866 | L4: 0 | M4: =IF(L4>2500, "High Sales", "Low Sales") -> Low Sales | N4: =IF(OR(ISBLANK(L4), L4="", L4=0), "Grade C", IF(L4>=4000, "Grade A", IF(L4>=2000, "Grade B", "Grade C"))) -> Grade C | O4: 10 | P4: 10 | Q4: Shipped | R4: 10 | S4: =CONCATENATE(OrdersTable[[#This Row],[Clean_ID]],"-",OrdersTable[[#This Row],[Clean_Region]],"-",OrdersTable[[#This Row],[Clean_Product]]) -> 1002-CENTRAL-Electronics
A5: ORD1003 | B5: =RIGHT(A5, 4) -> 1003 | C5: Michele Johnson | D5: =PROPER(TRIM(C5)) -> Michele Johnson | E5: East | F5: =UPPER(TRIM(E5)) -> EAST | G5: Electronics | H5: =PROPER(TRIM(G5)) -> Electronics | I5: 2026-02-16 | J5: 46069 | L5: 0 | M5: =IF(L5>2500, "High Sales", "Low Sales") -> Low Sales | N5: =IF(OR(ISBLANK(L5), L5="", L5=0), "Grade C", IF(L5>=4000, "Grade A", IF(L5>=2000, "Grade B", "Grade C"))) -> Grade C | O5: 15 | P5: 15 | Q5: Pending | R5: 4 | S5: =CONCATENATE(OrdersTable[[#This Row],[Clean_ID]],"-",OrdersTable[[#This Row],[Clean_Region]],"-",OrdersTable[[#This Row],[Clean_Product]]) -> 1003-EAST-Electronics
A6: ORD1004 | B6: =RIGHT(A6, 4) -> 1004 | C6: Kimberly Peck | D6: =PROPER(TRIM(C6)) -> Kimberly Peck | E6: East | F6: =UPPER(TRIM(E6)) -> EAST | G6: Electronics | H6: =PROPER(TRIM(G6)) -> Electronics | I6: 04/04/2024 | J6: 45386 | L6: 0 | M6: =IF(L6>2500, "High Sales", "Low Sales") -> Low Sales | N6: =IF(OR(ISBLANK(L6), L6="", L6=0), "Grade C", IF(L6>=4000, "Grade A", IF(L6>=2000, "Grade B", "Grade C"))) -> Grade C | P6: 0 | Q6: Cancelled | R6: 13 | S6: =CONCATENATE(OrdersTable[[#This Row],[Clean_ID]],"-",OrdersTable[[#This Row],[Clean_Region]],"-",OrdersTable[[#This Row],[Clean_Product]]) -> 1004-EAST-Electronics
A7: ORD1005 | B7: =RIGHT(A7, 4) -> 1005 | D7: =PROPER(TRIM(C7)) | E7: North | F7: =UPPER(TRIM(E7)) -> NORTH | G7: electronics | H7: =PROPER(TRIM(G7)) -> Electronics | I7: 2025-07-03 | J7: 45841 | L7: 0 | M7: =IF(L7>2500, "High Sales", "Low Sales") -> Low Sales | N7: =IF(OR(ISBLANK(L7), L7="", L7=0), "Grade C", IF(L7>=4000, "Grade A", IF(L7>=2000, "Grade B", "Grade C"))) -> Grade C | O7: 5 | P7: 5 | Q7: Returned | R7: 5 | S7: =CONCATENATE(OrdersTable[[#This Row],[Clean_ID]],"-",OrdersTable[[#This Row],[Clean_Region]],"-",OrdersTable[[#This Row],[Clean_Product]]) -> 1005-NORTH-Electronics
A8: ORD1006 | B8: =RIGHT(A8, 4) -> 1006 | C8: Jonathan Sanchez | D8: =PROPER(TRIM(C8)) -> Jonathan Sanchez | E8: north | F8: =UPPER(TRIM(E8)) -> NORTH | G8: Office Supplies | H8: =PROPER(TRIM(G8)) -> Office Supplies | I8: 2025-08-14 | J8: 45883 | K8: 3537.63 | L8: 3537.63 | M8: =IF(L8>2500, "High Sales", "Low Sales") -> High Sales | N8: =IF(OR(ISBLANK(L8), L8="", L8=0), "Grade C", IF(L8>=4000, "Grade A", IF(L8>=2000, "Grade B", "Grade C"))) -> Grade B | O8: 10 | P8: 10 | Q8: Cancelled | R8: 2 | S8: =CONCATENATE(OrdersTable[[#This Row],[Clean_ID]],"-",OrdersTable[[#This Row],[Clean_Region]],"-",OrdersTable[[#This Row],[Clean_Product]]) -> 1006-NORTH-Office Supplies
A9: ORD1007 | B9: =RIGHT(A9, 4) -> 1007 | C9: Candice Lewis | D9: =PROPER(TRIM(C9)) -> Candice Lewis | E9: South | F9: =UPPER(TRIM(E9)) -> SOUTH | G9: Electronics | H9: =PROPER(TRIM(G9)) -> Electronics | I9: 24/01/2025 | J9: 45681 | L9: 0 | M9: =IF(L9>2500, "High Sales", "Low Sales") -> Low Sales | N9: =IF(OR(ISBLANK(L9), L9="", L9=0), "Grade C", IF(L9>=4000, "Grade A", IF(L9>=2000, "Grade B", "Grade C"))) -> Grade C | O9: 10 | P9: 10 | Q9: Cancelled | R9: 6 | S9: =CONCATENATE(OrdersTable[[#This Row],[Clean_ID]],"-",OrdersTable[[#This Row],[Clean_Region]],"-",OrdersTable[[#This Row],[Clean_Product]]) -> 1007-SOUTH-Electronics
A10: ORD1008 | B10: =RIGHT(A10, 4) -> 1008 | C10: Jessica Torres | D10: =PROPER(TRIM(C10)) -> Jessica Torres | E10: South | F10: =UPPER(TRIM(E10)) -> SOUTH | G10: Office Supplies | H10: =PROPER(TRIM(G10)) -> Office Supplies | I10: 12-19-2025 | J10: 46010 | K10: 3257.78 | L10: 3257.78 | M10: =IF(L10>2500, "High Sales", "Low Sales") -> High Sales | N10: =IF(OR(ISBLANK(L10), L10="", L10=0), "Grade C", IF(L10>=4000, "Grade A", IF(L10>=2000, "Grade B", "Grade C"))) -> Grade B | P10: 0 | Q10: Pending | R10: 3 | S10: =CONCATENATE(OrdersTable[[#This Row],[Clean_ID]],"-",OrdersTable[[#This Row],[Clean_Region]],"-",OrdersTable[[#This Row],[Clean_Product]]) -> 1008-SOUTH-Office Supplies
A11: ORD1009 | B11: =RIGHT(A11, 4) -> 1009 | C11: Arthur Perry | D11: =PROPER(TRIM(C11)) -> Arthur Perry | E11: West | F11: =UPPER(TRIM(E11)) -> WEST | G11: electronics | H11: =PROPER(TRIM(G11)) -> Electronics | I11: 10-03-2024 | J11: 45568 | K11: 3456.4 | L11: 3456.4 | M11: =IF(L11>2500, "High Sales", "Low Sales") -> High Sales | N11: =IF(OR(ISBLANK(L11), L11="", L11=0), "Grade C", IF(L11>=4000, "Grade A", IF(L11>=2000, "Grade B", "Grade C"))) -> Grade B | O11: 15 | P11: 15 | Q11: Delivered | R11: 4 | S11: =CONCATENATE(OrdersTable[[#This Row],[Clean_ID]],"-",OrdersTable[[#This Row],[Clean_Region]],"-",OrdersTable[[#This Row],[Clean_Product]]) -> 1009-WEST-Electronics
A12: ORD1010 | B12: =RIGHT(A12, 4) -> 1010 | C12: Justin Gonzalez | D12: =PROPER(TRIM(C12)) -> Justin Gonzalez | E12: North | F12: =UPPER(TRIM(E12)) -> NORTH | G12: Office Supplies | H12: =PROPER(TRIM(G12)) -> Office Supplies | I12: 14/02/2025 | J12: 45702 | K12: N/A | L12: 0 | M12: =IF(L12>2500, "High Sales", "Low Sales") -> Low Sales | N12: =IF(OR(ISBLANK(L12), L12="", L12=0), "Grade C", IF(L12>=4000, "Grade A", IF(L12>=2000, "Grade B", "Grade C"))) -> Grade C | O12: 10 | P12: 10 | Q12: Shipped | R12: 7 | S12: =CONCATENATE(OrdersTable[[#This Row],[Clean_ID]],"-",OrdersTable[[#This Row],[Clean_Region]],"-",OrdersTable[[#This Row],[Clean_Product]]) -> 1010-NORTH-Office Supplies
A13: ORD1011 | B13: =RIGHT(A13, 4) -> 1011 | C13: Donald Mills | D13: =PROPER(TRIM(C13)) -> Donald Mills | E13: north | F13: =UPPER(TRIM(E13)) -> NORTH | G13: electronics | H13: =PROPER(TRIM(G13)) -> Electronics | I13: 26/05/2024 | J13: 45438 | L13: 0 | M13: =IF(L13>2500, "High Sales", "Low Sales") -> Low Sales | N13: =IF(OR(ISBLANK(L13), L13="", L13=0), "Grade C", IF(L13>=4000, "Grade A", IF(L13>=2000, "Grade B", "Grade C"))) -> Grade C | P13: 0 | Q13: Shipped | R13: 15 | S13: =CONCATENATE(OrdersTable[[#This Row],[Clean_ID]],"-",OrdersTable[[#This Row],[Clean_Region]],"-",OrdersTable[[#This Row],[Clean_Product]]) -> 1011-NORTH-Electronics
A14: ORD1012 | B14: =RIGHT(A14, 4) -> 1012 | C14: Thomas Montgomery | D14: =PROPER(TRIM(C14)) -> Thomas Montgomery | E14: Central | F14: =UPPER(TRIM(E14)) -> CENTRAL | G14: electronics | H14: =PROPER(TRIM(G14)) -> Electronics | I14: 2025-01-05 | J14: 45662 | K14: 4986.76 | L14: 4986.76 | M14: =IF(L14>2500, "High Sales", "Low Sales") -> High Sales | N14: =IF(OR(ISBLANK(L14), L14="", L14=0), "Grade C", IF(L14>=4000, "Grade A", IF(L14>=2000, "Grade B", "Grade C"))) -> Grade A | P14: 0 | Q14: Shipped | R14: 2 | S14: =CONCATENATE(OrdersTable[[#This Row],[Clean_ID]],"-",OrdersTable[[#This Row],[Clean_Region]],"-",OrdersTable[[#This Row],[Clean_Product]]) -> 1012-CENTRAL-Electronics
A15: ORD1013 | B15: =RIGHT(A15, 4) -> 1013 | C15: John Hernandez | D15: =PROPER(TRIM(C15)) -> John Hernandez | E15: North | F15: =UPPER(TRIM(E15)) -> NORTH | G15: Electronics | H15: =PROPER(TRIM(G15)) -> Electronics | I15: 06-05-2024 | J15: 45448 | L15: 0 | M15: =IF(L15>2500, "High Sales", "Low Sales") -> Low Sales | N15: =IF(OR(ISBLANK(L15), L15="", L15=0), "Grade C", IF(L15>=4000, "Grade A", IF(L15>=2000, "Grade B", "Grade C"))) -> Grade C | P15: 0 | Q15: Delivered | R15: 7 | S15: =CONCATENATE(OrdersTable[[#This Row],[Clean_ID]],"-",OrdersTable[[#This Row],[Clean_Region]],"-",OrdersTable[[#This Row],[Clean_Product]]) -> 1013-NORTH-Electronics
A16: ORD1014 | B16: =RIGHT(A16, 4) -> 1014 | C16: Paul Garza | D16: =PROPER(TRIM(C16)) -> Paul Garza | E16: West | F16: =UPPER(TRIM(E16)) -> WEST | G16: electronics | H16: =PROPER(TRIM(G16)) -> Electronics | I16: 25/06/2025 | J16: 45833 | K16: 4856.84 | L16: 4856.84 | M16: =IF(L16>2500, "High Sales", "Low Sales") -> High Sales | N16: =IF(OR(ISBLANK(L16), L16="", L16=0), "Grade C", IF(L16>=4000, "Grade A", IF(L16>=2000, "Grade B", "Grade C"))) -> Grade A | O16: 5 | P16: 5 | Q16: Returned | R16: 13 | S16: =CONCATENATE(OrdersTable[[#This Row],[Clean_ID]],"-",OrdersTable[[#This Row],[Clean_Region]],"-",OrdersTable[[#This Row],[Clean_Product]]) -> 1014-WEST-Electronics
A17: ORD1015 | B17: =RIGHT(A17, 4) -> 1015 | C17: Matthew Alvarez | D17: =PROPER(TRIM(C17)) -> Matthew Alvarez | E17: East | F17: =UPPER(TRIM(E17)) -> EAST | G17: Office Supplies | H17: =PROPER(TRIM(G17)) -> Office Supplies | I17: 24/04/2024 | J17: 45406 | L17: 0 | M17: =IF(L17>2500, "High Sales", "Low Sales") -> Low Sales | N17: =IF(OR(ISBLANK(L17), L17="", L17=0), "Grade C", IF(L17>=4000, "Grade A", IF(L17>=2000, "Grade B", "Grade C"))) -> Grade C | O17: 5 | P17: 5 | Q17: Cancelled | R17: 9 | S17: =CONCATENATE(OrdersTable[[#This Row],[Clean_ID]],"-",OrdersTable[[#This Row],[Clean_Region]],"-",OrdersTable[[#This Row],[Clean_Product]]) -> 1015-EAST-Office Supplies
A18: ORD1016 | B18: =RIGHT(A18, 4) -> 1016 | C18: Troy Cortez | D18: =PROPER(TRIM(C18)) -> Troy Cortez | E18: South | F18: =UPPER(TRIM(E18)) -> SOUTH | G18: Electronics | H18: =PROPER(TRIM(G18)) -> Electronics | I18: 02/10/2025 | J18: 45698 | K18: 4216.26 | L18: 4216.26 | M18: =IF(L18>2500, "High Sales", "Low Sales") -> High Sales | N18: =IF(OR(ISBLANK(L18), L18="", L18=0), "Grade C", IF(L18>=4000, "Grade A", IF(L18>=2000, "Grade B", "Grade C"))) -> Grade A | O18: 10 | P18: 10 | Q18: Cancelled | R18: 13 | S18: =CONCATENATE(OrdersTable[[#This Row],[Clean_ID]],"-",OrdersTable[[#This Row],[Clean_Region]],"-",OrdersTable[[#This Row],[Clean_Product]]) -> 1016-SOUTH-Electronics
A19: ORD1017 | B19: =RIGHT(A19, 4) -> 1017 | C19: Thomas Walls | D19: =PROPER(TRIM(C19)) -> Thomas Walls | E19: South | F19: =UPPER(TRIM(E19)) -> SOUTH | G19: Electronics | H19: =PROPER(TRIM(G19)) -> Electronics | I19: 05/09/2025 | J19: 45786 | K19: 2468.6 | L19: 2468.6 | M19: =IF(L19>2500, "High Sales", "Low Sales") -> Low Sales | N19: =IF(OR(ISBLANK(L19), L19="", L19=0), "Grade C", IF(L19>=4000, "Grade A", IF(L19>=2000, "Grade B", "Grade C"))) -> Grade B | O19: 15 | P19: 15 | Q19: Cancelled | R19: 4 | S19: =CONCATENATE(OrdersTable[[#This Row],[Clean_ID]],"-",OrdersTable[[#This Row],[Clean_Region]],"-",OrdersTable[[#This Row],[Clean_Product]]) -> 1017-SOUTH-Electronics
A20: ORD1018 | B20: =RIGHT(A20, 4) -> 1018 | C20: Jon Lee | D20: =PROPER(TRIM(C20)) -> Jon Lee | E20: North | F20: =UPPER(TRIM(E20)) -> NORTH | G20: Furniture | H20: =PROPER(TRIM(G20)) -> Furniture | I20: 2025-08-03 | J20: 45872 | L20: 0 | M20: =IF(L20>2500, "High Sales", "Low Sales") -> Low Sales | N20: =IF(OR(ISBLANK(L20), L20="", L20=0), "Grade C", IF(L20>=4000, "Grade A", IF(L20>=2000, "Grade B", "Grade C"))) -> Grade C | O20: 5 | P20: 5 | Q20: Returned | R20: 13 | S20: =CONCATENATE(OrdersTable[[#This Row],[Clean_ID]],"-",OrdersTable[[#This Row],[Clean_Region]],"-",OrdersTable[[#This Row],[Clean_Product]]) -> 1018-NORTH-Furniture
A21: ORD1019 | B21: =RIGHT(A21, 4) -> 1019 | C21: Christopher Mueller | D21: =PROPER(TRIM(C21)) -> Christopher Mueller | E21: South | F21: =UPPER(TRIM(E21)) -> SOUTH | G21: Furniture | H21: =PROPER(TRIM(G21)) -> Furniture | I21: 06/11/2025 | J21: 45819 | K21: 4736.9 | L21: 4736.9 | M21: =IF(L21>2500, "High Sales", "Low Sales") -> High Sales | N21: =IF(OR(ISBLANK(L21), L21="", L21=0), "Grade C", IF(L21>=4000, "Grade A", IF(L21>=2000, "Grade B", "Grade C"))) -> Grade A | O21: 15 | P21: 15 | Q21: Returned | R21: 14 | S21: =CONCATENATE(OrdersTable[[#This Row],[Clean_ID]],"-",OrdersTable[[#This Row],[Clean_Region]],"-",OrdersTable[[#This Row],[Clean_Product]]) -> 1019-SOUTH-Furniture
A22: ORD1020 | B22: =RIGHT(A22, 4) -> 1020 | C22: Leslie Moore | D22: =PROPER(TRIM(C22)) -> Leslie Moore | E22: Central | F22: =UPPER(TRIM(E22)) -> CENTRAL | G22: electronics | H22: =PROPER(TRIM(G22)) -> Electronics | I22: 08-04-2024 | J22: 45508 | K22: 3788.56 | L22: 3788.56 | M22: =IF(L22>2500, "High Sales", "Low Sales") -> High Sales | N22: =IF(OR(ISBLANK(L22), L22="", L22=0), "Grade C", IF(L22>=4000, "Grade A", IF(L22>=2000, "Grade B", "Grade C"))) -> Grade B | O22: 15 | P22: 15 | Q22: Shipped | R22: 11 | S22: =CONCATENATE(OrdersTable[[#This Row],[Clean_ID]],"-",OrdersTable[[#This Row],[Clean_Region]],"-",OrdersTable[[#This Row],[Clean_Product]]) -> 1020-CENTRAL-Electronics
A23: ORD1021 | B23: =RIGHT(A23, 4) -> 1021 | C23: Frances Mitchell | D23: =PROPER(TRIM(C23)) -> Frances Mitchell | E23: north | F23: =UPPER(TRIM(E23)) -> NORTH | G23: Office Supplies | H23: =PROPER(TRIM(G23)) -> Office Supplies | I23: 03-24-2025 | J23: 45740 | K23: 2284.86 | L23: 2284.86 | M23: =IF(L23>2500, "High Sales", "Low Sales") -> Low Sales | N23: =IF(OR(ISBLANK(L23), L23="", L23=0), "Grade C", IF(L23>=4000, "Grade A", IF(L23>=2000, "Grade B", "Grade C"))) -> Grade B | O23: 10 | P23: 10 | Q23: Delivered | R23: 6 | S23: =CONCATENATE(OrdersTable[[#This Row],[Clean_ID]],"-",OrdersTable[[#This Row],[Clean_Region]],"-",OrdersTable[[#This Row],[Clean_Product]]) -> 1021-NORTH-Office Supplies
A24: ORD1022 | B24: =RIGHT(A24, 4) -> 1022 | C24: Miguel Smith | D24: =PROPER(TRIM(C24)) -> Miguel Smith | E24: North | F24: =UPPER(TRIM(E24)) -> NORTH | G24: Furniture | H24: =PROPER(TRIM(G24)) -> Furniture | I24: 2025-08-25 | J24: 45894 | K24: 85.59 | L24: 85.59 | M24: =IF(L24>2500, "High Sales", "Low Sales") -> Low Sales | N24: =IF(OR(ISBLANK(L24), L24="", L24=0), "Grade C", IF(L24>=4000, "Grade A", IF(L24>=2000, "Grade B", "Grade C"))) -> Grade C | O24: 10 | P24: 10 | Q24: Delivered | R24: 15 | S24: =CONCATENATE(OrdersTable[[#This Row],[Clean_ID]],"-",OrdersTable[[#This Row],[Clean_Region]],"-",OrdersTable[[#This Row],[Clean_Product]]) -> 1022-NORTH-Furniture
A25: ORD1023 | B25: =RIGHT(A25, 4) -> 1023 | C25: Edward Johnson | D25: =PROPER(TRIM(C25)) -> Edward Johnson | E25: North | F25: =UPPER(TRIM(E25)) -> NORTH | G25: Office Supplies | H25: =PROPER(TRIM(G25)) -> Office Supplies | I25: 03-13-2024 | J25: 45364 | L25: 0 | M25: =IF(L25>2500, "High Sales", "Low Sales") -> Low Sales | N25: =IF(OR(ISBLANK(L25), L25="", L25=0), "Grade C", IF(L25>=4000, "Grade A", IF(L25>=2000, "Grade B", "Grade C"))) -> Grade C | O25: 10 | P25: 10 | Q25: Returned | R25: 3 | S25: =CONCATENATE(OrdersTable[[#This Row],[Clean_ID]],"-",OrdersTable[[#This Row],[Clean_Region]],"-",OrdersTable[[#This Row],[Clean_Product]]) -> 1023-NORTH-Office Supplies
A26: ORD1024 | B26: =RIGHT(A26, 4) -> 1024 | C26: Aaron Young | D26: =PROPER(TRIM(C26)) -> Aaron Young | E26: north | F26: =UPPER(TRIM(E26)) -> NORTH | G26: electronics | H26: =PROPER(TRIM(G26)) -> Electronics | I26: 05/09/2024 | J26: 45421 | K26: 4047.11 | L26: 4047.11 | M26: =IF(L26>2500, "High Sales", "Low Sales") -> High Sales | N26: =IF(OR(ISBLANK(L26), L26="", L26=0), "Grade C", IF(L26>=4000, "Grade A", IF(L26>=2000, "Grade B", "Grade C"))) -> Grade A | O26: 5 | P26: 5 | Q26: Delivered | R26: 11 | S26: =CONCATENATE(OrdersTable[[#This Row],[Clean_ID]],"-",OrdersTable[[#This Row],[Clean_Region]],"-",OrdersTable[[#This Row],[Clean_Product]]) -> 1024-NORTH-Electronics
A27: ORD1025 | B27: =RIGHT(A27, 4) -> 1025 | C27: Julie Bentley | D27: =PROPER(TRIM(C27)) -> Julie Bentley | E27: West | F27: =UPPER(TRIM(E27)) -> WEST | G27: Office Supplies | H27: =PROPER(TRIM(G27)) -> Office Supplies | I27: 09/03/2025 | J27: 45903 | K27: 2361.77 | L27: 2361.77 | M27: =IF(L27>2500, "High Sales", "Low Sales") -> Low Sales | N27: =IF(OR(ISBLANK(L27), L27="", L27=0), "Grade C", IF(L27>=4000, "Grade A", IF(L27>=2000, "Grade B", "Grade C"))) -> Grade B | O27: 5 | P27: 5 | Q27: Delivered | R27: 7 | S27: =CONCATENATE(OrdersTable[[#This Row],[Clean_ID]],"-",OrdersTable[[#This Row],[Clean_Region]],"-",OrdersTable[[#This Row],[Clean_Product]]) -> 1025-WEST-Office Supplies
A28: ORD1026 | B28: =RIGHT(A28, 4) -> 1026 | C28: Ray Mckinney | D28: =PROPER(TRIM(C28)) -> Ray Mckinney | E28: north | F28: =UPPER(TRIM(E28)) -> NORTH | G28: Office Supplies | H28: =PROPER(TRIM(G28)) -> Office Supplies | I28: 2026-03-30 | J28: 46111 | K28: 1280.85 | L28: 1280.85 | M28: =IF(L28>2500, "High Sales", "Low Sales") -> Low Sales | N28: =IF(OR(ISBLANK(L28), L28="", L28=0), "Grade C", IF(L28>=4000, "Grade A", IF(L28>=2000, "Grade B", "Grade C"))) -> Grade C | P28: 0 | Q28: Shipped | R28: 3 | S28: =CONCATENATE(OrdersTable[[#This Row],[Clean_ID]],"-",OrdersTable[[#This Row],[Clean_Region]],"-",OrdersTable[[#This Row],[Clean_Product]]) -> 1026-NORTH-Office Supplies
A29: ORD1027 | B29: =RIGHT(A29, 4) -> 1027 | C29: Nicole Berry | D29: =PROPER(TRIM(C29)) -> Nicole Berry | E29: West | F29: =UPPER(TRIM(E29)) -> WEST | G29: Furniture | H29: =PROPER(TRIM(G29)) -> Furniture | I29: 12/10/2024 | J29: 45636 | K29: 1286.54 | L29: 1286.54 | M29: =IF(L29>2500, "High Sales", "Low Sales") -> Low Sales | N29: =IF(OR(ISBLANK(L29), L29="", L29=0), "Grade C", IF(L29>=4000, "Grade A", IF(L29>=2000, "Grade B", "Grade C"))) -> Grade C | O29: 20 | P29: 20 | Q29: Returned | R29: 2 | S29: =CONCATENATE(OrdersTable[[#This Row],[Clean_ID]],"-",OrdersTable[[#This Row],[Clean_Region]],"-",OrdersTable[[#This Row],[Clean_Product]]) -> 1027-WEST-Furniture
A30: ORD1028 | B30: =RIGHT(A30, 4) -> 1028 | C30: Christina Hill | D30: =PROPER(TRIM(C30)) -> Christina Hill | E30: North | F30: =UPPER(TRIM(E30)) -> NORTH | G30: Electronics | H30: =PROPER(TRIM(G30)) -> Electronics | I30: 2024-04-05 | J30: 45387 | L30: 0 | M30: =IF(L30>2500, "High Sales", "Low Sales") -> Low Sales | N30: =IF(OR(ISBLANK(L30), L30="", L30=0), "Grade C", IF(L30>=4000, "Grade A", IF(L30>=2000, "Grade B", "Grade C"))) -> Grade C | O30: 20 | P30: 20 | Q30: Pending | R30: 14 | S30: =CONCATENATE(OrdersTable[[#This Row],[Clean_ID]],"-",OrdersTable[[#This Row],[Clean_Region]],"-",OrdersTable[[#This Row],[Clean_Product]]) -> 1028-NORTH-Electronics
A31: ORD1029 | B31: =RIGHT(A31, 4) -> 1029 | C31: Kevin Buck | D31: =PROPER(TRIM(C31)) -> Kevin Buck | E31: West | F31: =UPPER(TRIM(E31)) -> WEST | G31: Electronics | H31: =PROPER(TRIM(G31)) -> Electronics | I31: 17/06/2024 | J31: 45460 | L31: 0 | M31: =IF(L31>2500, "High Sales", "Low Sales") -> Low Sales | N31: =IF(OR(ISBLANK(L31), L31="", L31=0), "Grade C", IF(L31>=4000, "Grade A", IF(L31>=2000, "Grade B", "Grade C"))) -> Grade C | O31: 15 | P31: 15 | Q31: Shipped | R31: 5 | S31: =CONCATENATE(OrdersTable[[#This Row],[Clean_ID]],"-",OrdersTable[[#This Row],[Clean_Region]],"-",OrdersTable[[#This Row],[Clean_Product]]) -> 1029-WEST-Electronics
A32: ORD1030 | B32: =RIGHT(A32, 4) -> 1030 | C32: Kenneth Johnson | D32: =PROPER(TRIM(C32)) -> Kenneth Johnson | E32: West | F32: =UPPER(TRIM(E32)) -> WEST | G32: electronics | H32: =PROPER(TRIM(G32)) -> Electronics | I32: 2024-06-07 | J32: 45450 | K32: 1518.7 | L32: 1518.7 | M32: =IF(L32>2500, "High Sales", "Low Sales") -> Low Sales | N32: =IF(OR(ISBLANK(L32), L32="", L32=0), "Grade C", IF(L32>=4000, "Grade A", IF(L32>=2000, "Grade B", "Grade C"))) -> Grade C | P32: 0 | Q32: Returned | R32: 1 | S32: =CONCATENATE(OrdersTable[[#This Row],[Clean_ID]],"-",OrdersTable[[#This Row],[Clean_Region]],"-",OrdersTable[[#This Row],[Clean_Product]]) -> 1030-WEST-Electronics
A33: ORD1031 | B33: =RIGHT(A33, 4) -> 1031 | C33: Michael Davis | D33: =PROPER(TRIM(C33)) -> Michael Davis | E33: north | F33: =UPPER(TRIM(E33)) -> NORTH | G33: Office Supplies | H33: =PROPER(TRIM(G33)) -> Office Supplies | I33: 2024-02-28 | J33: 45350 | K33: 2941.68 | L33: 2941.68 | M33: =IF(L33>2500, "High Sales", "Low Sales") -> High Sales | N33: =IF(OR(ISBLANK(L33), L33="", L33=0), "Grade C", IF(L33>=4000, "Grade A", IF(L33>=2000, "Grade B", "Grade C"))) -> Grade B | O33: 5 | P33: 5 | Q33: Returned | R33: 2 | S33: =CONCATENATE(OrdersTable[[#This Row],[Clean_ID]],"-",OrdersTable[[#This Row],[Clean_Region]],"-",OrdersTable[[#This Row],[Clean_Product]]) -> 1031-NORTH-Office Supplies
A34: ORD1032 | B34: =RIGHT(A34, 4) -> 1032 | C34: Madeline Powell | D34: =PROPER(TRIM(C34)) -> Madeline Powell | E34: South | F34: =UPPER(TRIM(E34)) -> SOUTH | G34: Electronics | H34: =PROPER(TRIM(G34)) -> Electronics | I34: 2025-09-01 | J34: 45901 | K34: 3392.3 | L34: 3392.3 | M34: =IF(L34>2500, "High Sales", "Low Sales") -> High Sales | N34: =IF(OR(ISBLANK(L34), L34="", L34=0), "Grade C", IF(L34>=4000, "Grade A", IF(L34>=2000, "Grade B", "Grade C"))) -> Grade B | O34: 20 | P34: 20 | Q34: Delivered | R34: 15 | S34: =CONCATENATE(OrdersTable[[#This Row],[Clean_ID]],"-",OrdersTable[[#This Row],[Clean_Region]],"-",OrdersTable[[#This Row],[Clean_Product]]) -> 1032-SOUTH-Electronics
A35: ORD1033 | B35: =RIGHT(A35, 4) -> 1033 | C35: Kelly Craig | D35: =PROPER(TRIM(C35)) -> Kelly Craig | E35: Central | F35: =UPPER(TRIM(E35)) -> CENTRAL | G35: Furniture | H35: =PROPER(TRIM(G35)) -> Furniture | I35: 08-15-2025 | J35: 45884 | K35: 246.72 | L35: 246.72 | M35: =IF(L35>2500, "High Sales", "Low Sales") -> Low Sales | N35: =IF(OR(ISBLANK(L35), L35="", L35=0), "Grade C", IF(L35>=4000, "Grade A", IF(L35>=2000, "Grade B", "Grade C"))) -> Grade C | O35: 20 | P35: 20 | Q35: Returned | R35: 10 | S35: =CONCATENATE(OrdersTable[[#This Row],[Clean_ID]],"-",OrdersTable[[#This Row],[Clean_Region]],"-",OrdersTable[[#This Row],[Clean_Product]]) -> 1033-CENTRAL-Furniture
A36: ORD1034 | B36: =RIGHT(A36, 4) -> 1034 | C36: Deborah Rodriguez | D36: =PROPER(TRIM(C36)) -> Deborah Rodriguez | E36: Central | F36: =UPPER(TRIM(E36)) -> CENTRAL | G36: Office Supplies | H36: =PROPER(TRIM(G36)) -> Office Supplies | I36: 2024-09-24 | J36: 45559 | L36: 0 | M36: =IF(L36>2500, "High Sales", "Low Sales") -> Low Sales | N36: =IF(OR(ISBLANK(L36), L36="", L36=0), "Grade C", IF(L36>=4000, "Grade A", IF(L36>=2000, "Grade B", "Grade C"))) -> Grade C | O36: 10 | P36: 10 | Q36: Cancelled | R36: 7 | S36: =CONCATENATE(OrdersTable[[#This Row],[Clean_ID]],"-",OrdersTable[[#This Row],[Clean_Region]],"-",OrdersTable[[#This Row],[Clean_Product]]) -> 1034-CENTRAL-Office Supplies
A37: ORD1035 | B37: =RIGHT(A37, 4) -> 1035 | C37: Tammy Mckay | D37: =PROPER(TRIM(C37)) -> Tammy Mckay | E37: South | F37: =UPPER(TRIM(E37)) -> SOUTH | G37: Office Supplies | H37: =PROPER(TRIM(G37)) -> Office Supplies | I37: 13/04/2025 | J37: 45760 | K37: 4648.64 | L37: 4648.64 | M37: =IF(L37>2500, "High Sales", "Low Sales") -> High Sales | N37: =IF(OR(ISBLANK(L37), L37="", L37=0), "Grade C", IF(L37>=4000, "Grade A", IF(L37>=2000, "Grade B", "Grade C"))) -> Grade A | O37: 5 | P37: 5 | Q37: Shipped | R37: 10 | S37: =CONCATENATE(OrdersTable[[#This Row],[Clean_ID]],"-",OrdersTable[[#This Row],[Clean_Region]],"-",OrdersTable[[#This Row],[Clean_Product]]) -> 1035-SOUTH-Office Supplies
A38: ORD1036 | B38: =RIGHT(A38, 4) -> 1036 | C38: Cynthia Crawford | D38: =PROPER(TRIM(C38)) -> Cynthia Crawford | E38: Central | F38: =UPPER(TRIM(E38)) -> CENTRAL | G38: Electronics | H38: =PROPER(TRIM(G38)) -> Electronics | I38: 03-16-2024 | J38: 45367 | L38: 0 | M38: =IF(L38>2500, "High Sales", "Low Sales") -> Low Sales | N38: =IF(OR(ISBLANK(L38), L38="", L38=0), "Grade C", IF(L38>=4000, "Grade A", IF(L38>=2000, "Grade B", "Grade C"))) -> Grade C | O38: 10 | P38: 10 | Q38: Cancelled | R38: 15 | S38: =CONCATENATE(OrdersTable[[#This Row],[Clean_ID]],"-",OrdersTable[[#This Row],[Clean_Region]],"-",OrdersTable[[#This Row],[Clean_Product]]) -> 1036-CENTRAL-Electronics
A39: ORD1037 | B39: =RIGHT(A39, 4) -> 1037 | C39: Benjamin Wright | D39: =PROPER(TRIM(C39)) -> Benjamin Wright | E39: North | F39: =UPPER(TRIM(E39)) -> NORTH | G39: Furniture | H39: =PROPER(TRIM(G39)) -> Furniture | I39: 13/01/2025 | J39: 45670 | L39: 0 | M39: =IF(L39>2500, "High Sales", "Low Sales") -> Low Sales | N39: =IF(OR(ISBLANK(L39), L39="", L39=0), "Grade C", IF(L39>=4000, "Grade A", IF(L39>=2000, "Grade B", "Grade C"))) -> Grade C | P39: 0 | Q39: Returned | R39: 1 | S39: =CONCATENATE(OrdersTable[[#This Row],[Clean_ID]],"-",OrdersTable[[#This Row],[Clean_Region]],"-",OrdersTable[[#This Row],[Clean_Product]]) -> 1037-NORTH-Furniture
A40: ORD1038 | B40: =RIGHT(A40, 4) -> 1038 | C40: Ryan Blake | D40: =PROPER(TRIM(C40)) -> Ryan Blake | E40: north | F40: =UPPER(TRIM(E40)) -> NORTH | G40: Office Supplies | H40: =PROPER(TRIM(G40)) -> Office Supplies | I40: 2025-11-10 | J40: 45971 | K40: 4697.7 | L40: 4697.7 | M40: =IF(L40>2500, "High Sales", "Low Sales") -> High Sales | N40: =IF(OR(ISBLANK(L40), L40="", L40=0), "Grade C", IF(L40>=4000, "Grade A", IF(L40>=2000, "Grade B", "Grade C"))) -> Grade A | O40: 15 | P40: 15 | Q40: Delivered | R40: 15 | S40: =CONCATENATE(OrdersTable[[#This Row],[Clean_ID]],"-",OrdersTable[[#This Row],[Clean_Region]],"-",OrdersTable[[#This Row],[Clean_Product]]) -> 1038-NORTH-Office Supplies
A41: ORD1039 | B41: =RIGHT(A41, 4) -> 1039 | C41: Kerry Morris | D41: =PROPER(TRIM(C41)) -> Kerry Morris | E41: North | F41: =UPPER(TRIM(E41)) -> NORTH | G41: Furniture | H41: =PROPER(TRIM(G41)) -> Furniture | I41: 05/10/2024 | J41: 45422 | L41: 0 | M41: =IF(L41>2500, "High Sales", "Low Sales") -> Low Sales | N41: =IF(OR(ISBLANK(L41), L41="", L41=0), "Grade C", IF(L41>=4000, "Grade A", IF(L41>=2000, "Grade B", "Grade C"))) -> Grade C | O41: 10 | P41: 10 | Q41: Cancelled | R41: 9 | S41: =CONCATENATE(OrdersTable[[#This Row],[Clean_ID]],"-",OrdersTable[[#This Row],[Clean_Region]],"-",OrdersTable[[#This Row],[Clean_Product]]) -> 1039-NORTH-Furniture
A42: ORD1040 | B42: =RIGHT(A42, 4) -> 1040 | C42: Mary Burns | D42: =PROPER(TRIM(C42)) -> Mary Burns | E42: West | F42: =UPPER(TRIM(E42)) -> WEST | G42: Office Supplies | H42: =PROPER(TRIM(G42)) -> Office Supplies | I42: 2024-02-22 | J42: 45344 | L42: 0 | M42: =IF(L42>2500, "High Sales", "Low Sales") -> Low Sales | N42: =IF(OR(ISBLANK(L42), L42="", L42=0), "Grade C", IF(L42>=4000, "Grade A", IF(L42>=2000, "Grade B", "Grade C"))) -> Grade C | O42: 5 | P42: 5 | Q42: Delivered | R42: 6 | S42: =CONCATENATE(OrdersTable[[#This Row],[Clean_ID]],"-",OrdersTable[[#This Row],[Clean_Region]],"-",OrdersTable[[#This Row],[Clean_Product]]) -> 1040-WEST-Office Supplies
A43: ORD1041 | B43: =RIGHT(A43, 4) -> 1041 | C43: Jill Nichols | D43: =PROPER(TRIM(C43)) -> Jill Nichols | E43: South | F43: =UPPER(TRIM(E43)) -> SOUTH | G43: Office Supplies | H43: =PROPER(TRIM(G43)) -> Office Supplies | I43: 06-14-2024 | J43: 45457 | L43: 0 | M43: =IF(L43>2500, "High Sales", "Low Sales") -> Low Sales | N43: =IF(OR(ISBLANK(L43), L43="", L43=0), "Grade C", IF(L43>=4000, "Grade A", IF(L43>=2000, "Grade B", "Grade C"))) -> Grade C | P43: 0 | Q43: Delivered | R43: 2 | S43: =CONCATENATE(OrdersTable[[#This Row],[Clean_ID]],"-",OrdersTable[[#This Row],[Clean_Region]],"-",OrdersTable[[#This Row],[Clean_Product]]) -> 1041-SOUTH-Office Supplies
A44: ORD1042 | B44: =RIGHT(A44, 4) -> 1042 | C44: Melissa Ramirez | D44: =PROPER(TRIM(C44)) -> Melissa Ramirez | E44: North | F44: =UPPER(TRIM(E44)) -> NORTH | G44: Furniture | H44: =PROPER(TRIM(G44)) -> Furniture | I44: 2025-07-12 | J44: 45850 | K44: 4181.25 | L44: 4181.25 | M44: =IF(L44>2500, "High Sales", "Low Sales") -> High Sales | N44: =IF(OR(ISBLANK(L44), L44="", L44=0), "Grade C", IF(L44>=4000, "Grade A", IF(L44>=2000, "Grade B", "Grade C"))) -> Grade A | O44: 20 | P44: 20 | Q44: Pending | R44: 1 | S44: =CONCATENATE(OrdersTable[[#This Row],[Clean_ID]],"-",OrdersTable[[#This Row],[Clean_Region]],"-",OrdersTable[[#This Row],[Clean_Product]]) -> 1042-NORTH-Furniture
A45: ORD1043 | B45: =RIGHT(A45, 4) -> 1043 | C45: Wendy Nguyen | D45: =PROPER(TRIM(C45)) -> Wendy Nguyen | E45: East | F45: =UPPER(TRIM(E45)) -> EAST | G45: Office Supplies | H45: =PROPER(TRIM(G45)) -> Office Supplies | I45: 2026-03-26 | J45: 46107 | K45: 4499.68 | L45: 4499.68 | M45: =IF(L45>2500, "High Sales", "Low Sales") -> High Sales | N45: =IF(OR(ISBLANK(L45), L45="", L45=0), "Grade C", IF(L45>=4000, "Grade A", IF(L45>=2000, "Grade B", "Grade C"))) -> Grade A | O45: 10 | P45: 10 | Q45: Delivered | R45: 6 | S45: =CONCATENATE(OrdersTable[[#This Row],[Clean_ID]],"-",OrdersTable[[#This Row],[Clean_Region]],"-",OrdersTable[[#This Row],[Clean_Product]]) -> 1043-EAST-Office Supplies
A46: ORD1044 | B46: =RIGHT(A46, 4) -> 1044 | C46: Brittney Robinson | D46: =PROPER(TRIM(C46)) -> Brittney Robinson | E46: Central | F46: =UPPER(TRIM(E46)) -> CENTRAL | G46: electronics | H46: =PROPER(TRIM(G46)) -> Electronics | I46: 09-27-2025 | J46: 45927 | K46: 815.04 | L46: 815.04 | M46: =IF(L46>2500, "High Sales", "Low Sales") -> Low Sales | N46: =IF(OR(ISBLANK(L46), L46="", L46=0), "Grade C", IF(L46>=4000, "Grade A", IF(L46>=2000, "Grade B", "Grade C"))) -> Grade C | O46: 10 | P46: 10 | Q46: Pending | R46: 15 | S46: =CONCATENATE(OrdersTable[[#This Row],[Clean_ID]],"-",OrdersTable[[#This Row],[Clean_Region]],"-",OrdersTable[[#This Row],[Clean_Product]]) -> 1044-CENTRAL-Electronics
A47: ORD1045 | B47: =RIGHT(A47, 4) -> 1045 | C47: Mark Jensen Jr. | D47: =PROPER(TRIM(C47)) -> Mark Jensen Jr. | E47: West | F47: =UPPER(TRIM(E47)) -> WEST | G47: Electronics | H47: =PROPER(TRIM(G47)) -> Electronics | I47: 07-02-2024 | J47: 45475 | L47: 0 | M47: =IF(L47>2500, "High Sales", "Low Sales") -> Low Sales | N47: =IF(OR(ISBLANK(L47), L47="", L47=0), "Grade C", IF(L47>=4000, "Grade A", IF(L47>=2000, "Grade B", "Grade C"))) -> Grade C | O47: 10 | P47: 10 | Q47: Cancelled | R47: 3 | S47: =CONCATENATE(OrdersTable[[#This Row],[Clean_ID]],"-",OrdersTable[[#This Row],[Clean_Region]],"-",OrdersTable[[#This Row],[Clean_Product]]) -> 1045-WEST-Electronics
A48: ORD1046 | B48: =RIGHT(A48, 4) -> 1046 | C48: Carl Singleton Jr. | D48: =PROPER(TRIM(C48)) -> Carl Singleton Jr. | E48: north | F48: =UPPER(TRIM(E48)) -> NORTH | G48: Electronics | H48: =PROPER(TRIM(G48)) -> Electronics | I48: 2025-01-26 | J48: 45683 | K48: 4300.04 | L48: 4300.04 | M48: =IF(L48>2500, "High Sales", "Low Sales") -> High Sales | N48: =IF(OR(ISBLANK(L48), L48="", L48=0), "Grade C", IF(L48>=4000, "Grade A", IF(L48>=2000, "Grade B", "Grade C"))) -> Grade A | O48: 10 | P48: 10 | Q48: Shipped | R48: 6 | S48: =CONCATENATE(OrdersTable[[#This Row],[Clean_ID]],"-",OrdersTable[[#This Row],[Clean_Region]],"-",OrdersTable[[#This Row],[Clean_Product]]) -> 1046-NORTH-Electronics
A49: ORD1047 | B49: =RIGHT(A49, 4) -> 1047 | C49: Tanya Duncan | D49: =PROPER(TRIM(C49)) -> Tanya Duncan | E49: East | F49: =UPPER(TRIM(E49)) -> EAST | G49: Furniture | H49: =PROPER(TRIM(G49)) -> Furniture | I49: 2024-08-16 | J49: 45520 | L49: 0 | M49: =IF(L49>2500, "High Sales", "Low Sales") -> Low Sales | N49: =IF(OR(ISBLANK(L49), L49="", L49=0), "Grade C", IF(L49>=4000, "Grade A", IF(L49>=2000, "Grade B", "Grade C"))) -> Grade C | O49: 15 | P49: 15 | Q49: Cancelled | R49: 14 | S49: =CONCATENATE(OrdersTable[[#This Row],[Clean_ID]],"-",OrdersTable[[#This Row],[Clean_Region]],"-",OrdersTable[[#This Row],[Clean_Product]]) -> 1047-EAST-Furniture
A50: ORD1048 | B50: =RIGHT(A50, 4) -> 1048 | C50: Robert Wright | D50: =PROPER(TRIM(C50)) -> Robert Wright | E50: North | F50: =UPPER(TRIM(E50)) -> NORTH | G50: Office Supplies | H50: =PROPER(TRIM(G50)) -> Office Supplies | I50: 12-25-2024 | J50: 45651 | L50: 0 | M50: =IF(L50>2500, "High Sales", "Low Sales") -> Low Sales | N50: =IF(OR(ISBLANK(L50), L50="", L50=0), "Grade C", IF(L50>=4000, "Grade A", IF(L50>=2000, "Grade B", "Grade C"))) -> Grade C | O50: 5 | P50: 5 | Q50: Delivered | R50: 15 | S50: =CONCATENATE(OrdersTable[[#This Row],[Clean_ID]],"-",OrdersTable[[#This Row],[Clean_Region]],"-",OrdersTable[[#This Row],[Clean_Product]]) -> 1048-NORTH-Office Supplies
A51: ORD1049 | B51: =RIGHT(A51, 4) -> 1049 | C51: Jason Kelly | D51: =PROPER(TRIM(C51)) -> Jason Kelly | E51: East | F51: =UPPER(TRIM(E51)) -> EAST | G51: Furniture | H51: =PROPER(TRIM(G51)) -> Furniture | I51: 17/08/2025 | J51: 45886 | L51: 0 | M51: =IF(L51>2500, "High Sales", "Low Sales") -> Low Sales | N51: =IF(OR(ISBLANK(L51), L51="", L51=0), "Grade C", IF(L51>=4000, "Grade A", IF(L51>=2000, "Grade B", "Grade C"))) -> Grade C | O51: 15 | P51: 15 | Q51: Cancelled | R51: 7 | S51: =CONCATENATE(OrdersTable[[#This Row],[Clean_ID]],"-",OrdersTable[[#This Row],[Clean_Region]],"-",OrdersTable[[#This Row],[Clean_Product]]) -> 1049-EAST-Furniture
A52: ORD1050 | B52: =RIGHT(A52, 4) -> 1050 | C52: Joseph James | D52: =PROPER(TRIM(C52)) -> Joseph James | E52: Central | F52: =UPPER(TRIM(E52)) -> CENTRAL | G52: Electronics | H52: =PROPER(TRIM(G52)) -> Electronics | I52: 01-29-2025 | J52: 45686 | K52: 990.89 | L52: 990.89 | M52: =IF(L52>2500, "High Sales", "Low Sales") -> Low Sales | N52: =IF(OR(ISBLANK(L52), L52="", L52=0), "Grade C", IF(L52>=4000, "Grade A", IF(L52>=2000, "Grade B", "Grade C"))) -> Grade C | O52: 20 | P52: 20 | Q52: Delivered | R52: 9 | S52: =CONCATENATE(OrdersTable[[#This Row],[Clean_ID]],"-",OrdersTable[[#This Row],[Clean_Region]],"-",OrdersTable[[#This Row],[Clean_Product]]) -> 1050-CENTRAL-Electronics
A53: ORD1051 | B53: =RIGHT(A53, 4) -> 1051 | C53: Cindy Dixon | D53: =PROPER(TRIM(C53)) -> Cindy Dixon | E53: Central | F53: =UPPER(TRIM(E53)) -> CENTRAL | G53: Furniture | H53: =PROPER(TRIM(G53)) -> Furniture | I53: 07/01/2025 | J53: 45839 | L53: 0 | M53: =IF(L53>2500, "High Sales", "Low Sales") -> Low Sales | N53: =IF(OR(ISBLANK(L53), L53="", L53=0), "Grade C", IF(L53>=4000, "Grade A", IF(L53>=2000, "Grade B", "Grade C"))) -> Grade C | P53: 0 | Q53: Cancelled | R53: 11 | S53: =CONCATENATE(OrdersTable[[#This Row],[Clean_ID]],"-",OrdersTable[[#This Row],[Clean_Region]],"-",OrdersTable[[#This Row],[Clean_Product]]) -> 1051-CENTRAL-Furniture
A54: ORD1052 | B54: =RIGHT(A54, 4) -> 1052 | C54: Cheryl Vargas | D54: =PROPER(TRIM(C54)) -> Cheryl Vargas | E54: North | F54: =UPPER(TRIM(E54)) -> NORTH | G54: Office Supplies | H54: =PROPER(TRIM(G54)) -> Office Supplies | I54: 03/06/2025 | J54: 45722 | L54: 0 | M54: =IF(L54>2500, "High Sales", "Low Sales") -> Low Sales | N54: =IF(OR(ISBLANK(L54), L54="", L54=0), "Grade C", IF(L54>=4000, "Grade A", IF(L54>=2000, "Grade B", "Grade C"))) -> Grade C | O54: 20 | P54: 20 | Q54: Cancelled | R54: 9 | S54: =CONCATENATE(OrdersTable[[#This Row],[Clean_ID]],"-",OrdersTable[[#This Row],[Clean_Region]],"-",OrdersTable[[#This Row],[Clean_Product]]) -> 1052-NORTH-Office Supplies
A55: ORD1053 | B55: =RIGHT(A55, 4) -> 1053 | C55: Hayley Hawkins | D55: =PROPER(TRIM(C55)) -> Hayley Hawkins | E55: South | F55: =UPPER(TRIM(E55)) -> SOUTH | G55: Furniture | H55: =PROPER(TRIM(G55)) -> Furniture | I55: 03-06-2025 | J55: 45722 | K55: 4704.8 | L55: 4704.8 | M55: =IF(L55>2500, "High Sales", "Low Sales") -> High Sales | N55: =IF(OR(ISBLANK(L55), L55="", L55=0), "Grade C", IF(L55>=4000, "Grade A", IF(L55>=2000, "Grade B", "Grade C"))) -> Grade A | P55: 0 | Q55: Returned | R55: 5 | S55: =CONCATENATE(OrdersTable[[#This Row],[Clean_ID]],"-",OrdersTable[[#This Row],[Clean_Region]],"-",OrdersTable[[#This Row],[Clean_Product]]) -> 1053-SOUTH-Furniture
A56: ORD1054 | B56: =RIGHT(A56, 4) -> 1054 | C56: Brianna Charles | D56: =PROPER(TRIM(C56)) -> Brianna Charles | E56: West | F56: =UPPER(TRIM(E56)) -> WEST | G56: Electronics | H56: =PROPER(TRIM(G56)) -> Electronics | I56: 07/11/2024 | J56: 45484 | L56: 0 | M56: =IF(L56>2500, "High Sales", "Low Sales") -> Low Sales | N56: =IF(OR(ISBLANK(L56), L56="", L56=0), "Grade C", IF(L56>=4000, "Grade A", IF(L56>=2000, "Grade B", "Grade C"))) -> Grade C | O56: 20 | P56: 20 | Q56: Shipped | R56: 8 | S56: =CONCATENATE(OrdersTable[[#This Row],[Clean_ID]],"-",OrdersTable[[#This Row],[Clean_Region]],"-",OrdersTable[[#This Row],[Clean_Product]]) -> 1054-WEST-Electronics
A57: ORD1055 | B57: =RIGHT(A57, 4) -> 1055 | C57: Jacqueline Brooks | D57: =PROPER(TRIM(C57)) -> Jacqueline Brooks | E57: north | F57: =UPPER(TRIM(E57)) -> NORTH | G57: Furniture | H57: =PROPER(TRIM(G57)) -> Furniture | I57: 07/06/2025 | J57: 45844 | K57: 3978.99 | L57: 3978.99 | M57: =IF(L57>2500, "High Sales", "Low Sales") -> High Sales | N57: =IF(OR(ISBLANK(L57), L57="", L57=0), "Grade C", IF(L57>=4000, "Grade A", IF(L57>=2000, "Grade B", "Grade C"))) -> Grade B | O57: 5 | P57: 5 | Q57: Cancelled | R57: 9 | S57: =CONCATENATE(OrdersTable[[#This Row],[Clean_ID]],"-",OrdersTable[[#This Row],[Clean_Region]],"-",OrdersTable[[#This Row],[Clean_Product]]) -> 1055-NORTH-Furniture
A58: ORD1056 | B58: =RIGHT(A58, 4) -> 1056 | C58: Glenda Dean | D58: =PROPER(TRIM(C58)) -> Glenda Dean | E58: north | F58: =UPPER(TRIM(E58)) -> NORTH | G58: Office Supplies | H58: =PROPER(TRIM(G58)) -> Office Supplies | I58: 2024-04-05 | J58: 45387 | K58: 3380.34 | L58: 3380.34 | M58: =IF(L58>2500, "High Sales", "Low Sales") -> High Sales | N58: =IF(OR(ISBLANK(L58), L58="", L58=0), "Grade C", IF(L58>=4000, "Grade A", IF(L58>=2000, "Grade B", "Grade C"))) -> Grade B | O58: 10 | P58: 10 | Q58: Pending | R58: 1 | S58: =CONCATENATE(OrdersTable[[#This Row],[Clean_ID]],"-",OrdersTable[[#This Row],[Clean_Region]],"-",OrdersTable[[#This Row],[Clean_Product]]) -> 1056-NORTH-Office Supplies
A59: ORD1057 | B59: =RIGHT(A59, 4) -> 1057 | C59: Phillip Hanna | D59: =PROPER(TRIM(C59)) -> Phillip Hanna | E59: North | F59: =UPPER(TRIM(E59)) -> NORTH | G59: Furniture | H59: =PROPER(TRIM(G59)) -> Furniture | I59: 05-01-2025 | J59: 45778 | K59: 4256.2 | L59: 4256.2 | M59: =IF(L59>2500, "High Sales", "Low Sales") -> High Sales | N59: =IF(OR(ISBLANK(L59), L59="", L59=0), "Grade C", IF(L59>=4000, "Grade A", IF(L59>=2000, "Grade B", "Grade C"))) -> Grade A | O59: 20 | P59: 20 | Q59: Shipped | R59: 15 | S59: =CONCATENATE(OrdersTable[[#This Row],[Clean_ID]],"-",OrdersTable[[#This Row],[Clean_Region]],"-",OrdersTable[[#This Row],[Clean_Product]]) -> 1057-NORTH-Furniture
A60: ORD1058 | B60: =RIGHT(A60, 4) -> 1058 | C60: Jennifer Lambert | D60: =PROPER(TRIM(C60)) -> Jennifer Lambert | E60: north | F60: =UPPER(TRIM(E60)) -> NORTH | G60: Furniture | H60: =PROPER(TRIM(G60)) -> Furniture | I60: 01-05-2026 | J60: 46027 | L60: 0 | M60: =IF(L60>2500, "High Sales", "Low Sales") -> Low Sales | N60: =IF(OR(ISBLANK(L60), L60="", L60=0), "Grade C", IF(L60>=4000, "Grade A", IF(L60>=2000, "Grade B", "Grade C"))) -> Grade C | O60: 10 | P60: 10 | Q60: Pending | R60: 11 | S60: =CONCATENATE(OrdersTable[[#This Row],[Clean_ID]],"-",OrdersTable[[#This Row],[Clean_Region]],"-",OrdersTable[[#This Row],[Clean_Product]]) -> 1058-NORTH-Furniture
A61: ORD1059 | B61: =RIGHT(A61, 4) -> 1059 | C61: Alvin Munoz | D61: =PROPER(TRIM(C61)) -> Alvin Munoz | E61: north | F61: =UPPER(TRIM(E61)) -> NORTH | G61: Electronics | H61: =PROPER(TRIM(G61)) -> Electronics | I61: 2026-02-07 | J61: 46060 | K61: 3903.18 | L61: 3903.18 | M61: =IF(L61>2500, "High Sales", "Low Sales") -> High Sales | N61: =IF(OR(ISBLANK(L61), L61="", L61=0), "Grade C", IF(L61>=4000, "Grade A", IF(L61>=2000, "Grade B", "Grade C"))) -> Grade B | O61: 10 | P61: 10 | Q61: Returned | R61: 8 | S61: =CONCATENATE(OrdersTable[[#This Row],[Clean_ID]],"-",OrdersTable[[#This Row],[Clean_Region]],"-",OrdersTable[[#This Row],[Clean_Product]]) -> 1059-NORTH-Electronics
A62: ORD1060 | B62: =RIGHT(A62, 4) -> 1060 | C62: Amanda Pittman | D62: =PROPER(TRIM(C62)) -> Amanda Pittman | E62: North | F62: =UPPER(TRIM(E62)) -> NORTH | G62: Furniture | H62: =PROPER(TRIM(G62)) -> Furniture | I62: 04/05/2024 | J62: 45387 | L62: 0 | M62: =IF(L62>2500, "High Sales", "Low Sales") -> Low Sales | N62: =IF(OR(ISBLANK(L62), L62="", L62=0), "Grade C", IF(L62>=4000, "Grade A", IF(L62>=2000, "Grade B", "Grade C"))) -> Grade C | P62: 0 | Q62: Returned | R62: 10 | S62: =CONCATENATE(OrdersTable[[#This Row],[Clean_ID]],"-",OrdersTable[[#This Row],[Clean_Region]],"-",OrdersTable[[#This Row],[Clean_Product]]) -> 1060-NORTH-Furniture
A63: ORD1061 | B63: =RIGHT(A63, 4) -> 1061 | C63: Pamela Pope | D63: =PROPER(TRIM(C63)) -> Pamela Pope | E63: East | F63: =UPPER(TRIM(E63)) -> EAST | G63: electronics | H63: =PROPER(TRIM(G63)) -> Electronics | I63: 09-19-2025 | J63: 45919 | L63: 0 | M63: =IF(L63>2500, "High Sales", "Low Sales") -> Low Sales | N63: =IF(OR(ISBLANK(L63), L63="", L63=0), "Grade C", IF(L63>=4000, "Grade A", IF(L63>=2000, "Grade B", "Grade C"))) -> Grade C | P63: 0 | Q63: Shipped | R63: 15 | S63: =CONCATENATE(OrdersTable[[#This Row],[Clean_ID]],"-",OrdersTable[[#This Row],[Clean_Region]],"-",OrdersTable[[#This Row],[Clean_Product]]) -> 1061-EAST-Electronics
A64: ORD1062 | B64: =RIGHT(A64, 4) -> 1062 | C64: Corey Miller | D64: =PROPER(TRIM(C64)) -> Corey Miller | E64: South | F64: =UPPER(TRIM(E64)) -> SOUTH | G64: electronics | H64: =PROPER(TRIM(G64)) -> Electronics | I64: 05/04/2025 | J64: 45781 | L64: 0 | M64: =IF(L64>2500, "High Sales", "Low Sales") -> Low Sales | N64: =IF(OR(ISBLANK(L64), L64="", L64=0), "Grade C", IF(L64>=4000, "Grade A", IF(L64>=2000, "Grade B", "Grade C"))) -> Grade C | P64: 0 | Q64: Shipped | R64: 11 | S64: =CONCATENATE(OrdersTable[[#This Row],[Clean_ID]],"-",OrdersTable[[#This Row],[Clean_Region]],"-",OrdersTable[[#This Row],[Clean_Product]]) -> 1062-SOUTH-Electronics
A65: ORD1063 | B65: =RIGHT(A65, 4) -> 1063 | C65: Paula Hines | D65: =PROPER(TRIM(C65)) -> Paula Hines | E65: South | F65: =UPPER(TRIM(E65)) -> SOUTH | G65: Office Supplies | H65: =PROPER(TRIM(G65)) -> Office Supplies | I65: 2025-03-26 | J65: 45742 | K65: 3582.05 | L65: 3582.05 | M65: =IF(L65>2500, "High Sales", "Low Sales") -> High Sales | N65: =IF(OR(ISBLANK(L65), L65="", L65=0), "Grade C", IF(L65>=4000, "Grade A", IF(L65>=2000, "Grade B", "Grade C"))) -> Grade B | O65: 15 | P65: 15 | Q65: Cancelled | R65: 6 | S65: =CONCATENATE(OrdersTable[[#This Row],[Clean_ID]],"-",OrdersTable[[#This Row],[Clean_Region]],"-",OrdersTable[[#This Row],[Clean_Product]]) -> 1063-SOUTH-Office Supplies
A66: ORD1064 | B66: =RIGHT(A66, 4) -> 1064 | C66: Jason Hernandez | D66: =PROPER(TRIM(C66)) -> Jason Hernandez | E66: Central | F66: =UPPER(TRIM(E66)) -> CENTRAL | G66: Electronics | H66: =PROPER(TRIM(G66)) -> Electronics | I66: 2024-05-21 | J66: 45433 | K66: 1194.74 | L66: 1194.74 | M66: =IF(L66>2500, "High Sales", "Low Sales") -> Low Sales | N66: =IF(OR(ISBLANK(L66), L66="", L66=0), "Grade C", IF(L66>=4000, "Grade A", IF(L66>=2000, "Grade B", "Grade C"))) -> Grade C | O66: 10 | P66: 10 | Q66: Delivered | R66: 7 | S66: =CONCATENATE(OrdersTable[[#This Row],[Clean_ID]],"-",OrdersTable[[#This Row],[Clean_Region]],"-",OrdersTable[[#This Row],[Clean_Product]]) -> 1064-CENTRAL-Electronics
A67: ORD1065 | B67: =RIGHT(A67, 4) -> 1065 | C67: Mark Morris | D67: =PROPER(TRIM(C67)) -> Mark Morris | E67: West | F67: =UPPER(TRIM(E67)) -> WEST | G67: Office Supplies | H67: =PROPER(TRIM(G67)) -> Office Supplies | I67: 09/07/2025 | J67: 45907 | K67: 2108.08 | L67: 2108.08 | M67: =IF(L67>2500, "High Sales", "Low Sales") -> Low Sales | N67: =IF(OR(ISBLANK(L67), L67="", L67=0), "Grade C", IF(L67>=4000, "Grade A", IF(L67>=2000, "Grade B", "Grade C"))) -> Grade B | O67: 20 | P67: 20 | Q67: Shipped | R67: 15 | S67: =CONCATENATE(OrdersTable[[#This Row],[Clean_ID]],"-",OrdersTable[[#This Row],[Clean_Region]],"-",OrdersTable[[#This Row],[Clean_Product]]) -> 1065-WEST-Office Supplies
A68: ORD1066 | B68: =RIGHT(A68, 4) -> 1066 | C68: Sharon Lopez | D68: =PROPER(TRIM(C68)) -> Sharon Lopez | E68: Central | F68: =UPPER(TRIM(E68)) -> CENTRAL | G68: Electronics | H68: =PROPER(TRIM(G68)) -> Electronics | I68: 02-22-2026 | J68: 46075 | K68: 1932.89 | L68: 1932.89 | M68: =IF(L68>2500, "High Sales", "Low Sales") -> Low Sales | N68: =IF(OR(ISBLANK(L68), L68="", L68=0), "Grade C", IF(L68>=4000, "Grade A", IF(L68>=2000, "Grade B", "Grade C"))) -> Grade C | O68: 15 | P68: 15 | Q68: Cancelled | R68: 13 | S68: =CONCATENATE(OrdersTable[[#This Row],[Clean_ID]],"-",OrdersTable[[#This Row],[Clean_Region]],"-",OrdersTable[[#This Row],[Clean_Product]]) -> 1066-CENTRAL-Electronics
A69: ORD1067 | B69: =RIGHT(A69, 4) -> 1067 | C69: Ashley White | D69: =PROPER(TRIM(C69)) -> Ashley White | E69: West | F69: =UPPER(TRIM(E69)) -> WEST | G69: electronics | H69: =PROPER(TRIM(G69)) -> Electronics | I69: 07-05-2025 | J69: 45843 | K69: 3686.44 | L69: 3686.44 | M69: =IF(L69>2500, "High Sales", "Low Sales") -> High Sales | N69: =IF(OR(ISBLANK(L69), L69="", L69=0), "Grade C", IF(L69>=4000, "Grade A", IF(L69>=2000, "Grade B", "Grade C"))) -> Grade B | O69: 20 | P69: 20 | Q69: Pending | R69: 5 | S69: =CONCATENATE(OrdersTable[[#This Row],[Clean_ID]],"-",OrdersTable[[#This Row],[Clean_Region]],"-",OrdersTable[[#This Row],[Clean_Product]]) -> 1067-WEST-Electronics
A70: ORD1068 | B70: =RIGHT(A70, 4) -> 1068 | C70: Danny Diaz | D70: =PROPER(TRIM(C70)) -> Danny Diaz | E70: West | F70: =UPPER(TRIM(E70)) -> WEST | G70: electronics | H70: =PROPER(TRIM(G70)) -> Electronics | I70: 30/01/2024 | J70: 45321 | L70: 0 | M70: =IF(L70>2500, "High Sales", "Low Sales") -> Low Sales | N70: =IF(OR(ISBLANK(L70), L70="", L70=0), "Grade C", IF(L70>=4000, "Grade A", IF(L70>=2000, "Grade B", "Grade C"))) -> Grade C | O70: 10 | P70: 10 | Q70: Shipped | R70: 15 | S70: =CONCATENATE(OrdersTable[[#This Row],[Clean_ID]],"-",OrdersTable[[#This Row],[Clean_Region]],"-",OrdersTable[[#This Row],[Clean_Product]]) -> 1068-WEST-Electronics
A71: ORD1069 | B71: =RIGHT(A71, 4) -> 1069 | C71: Brian Freeman | D71: =PROPER(TRIM(C71)) -> Brian Freeman | E71: South | F71: =UPPER(TRIM(E71)) -> SOUTH | G71: Electronics | H71: =PROPER(TRIM(G71)) -> Electronics | I71: 02-07-2025 | J71: 45695 | K71: 2843.74 | L71: 2843.74 | M71: =IF(L71>2500, "High Sales", "Low Sales") -> High Sales | N71: =IF(OR(ISBLANK(L71), L71="", L71=0), "Grade C", IF(L71>=4000, "Grade A", IF(L71>=2000, "Grade B", "Grade C"))) -> Grade B | O71: 5 | P71: 5 | Q71: Shipped | R71: 3 | S71: =CONCATENATE(OrdersTable[[#This Row],[Clean_ID]],"-",OrdersTable[[#This Row],[Clean_Region]],"-",OrdersTable[[#This Row],[Clean_Product]]) -> 1069-SOUTH-Electronics
A72: ORD1070 | B72: =RIGHT(A72, 4) -> 1070 | C72: Tanya Jackson | D72: =PROPER(TRIM(C72)) -> Tanya Jackson | E72: West | F72: =UPPER(TRIM(E72)) -> WEST | G72: Furniture | H72: =PROPER(TRIM(G72)) -> Furniture | I72: 21/02/2024 | J72: 45343 | K72: 1926.56 | L72: 1926.56 | M72: =IF(L72>2500, "High Sales", "Low Sales") -> Low Sales | N72: =IF(OR(ISBLANK(L72), L72="", L72=0), "Grade C", IF(L72>=4000, "Grade A", IF(L72>=2000, "Grade B", "Grade C"))) -> Grade C | O72: 20 | P72: 20 | Q72: Cancelled | R72: 6 | S72: =CONCATENATE(OrdersTable[[#This Row],[Clean_ID]],"-",OrdersTable[[#This Row],[Clean_Region]],"-",OrdersTable[[#This Row],[Clean_Product]]) -> 1070-WEST-Furniture
A73: ORD1071 | B73: =RIGHT(A73, 4) -> 1071 | C73: Donald Mcclure MD | D73: =PROPER(TRIM(C73)) -> Donald Mcclure Md | E73: West | F73: =UPPER(TRIM(E73)) -> WEST | G73: Office Supplies | H73: =PROPER(TRIM(G73)) -> Office Supplies | I73: 09/02/2026 | J73: 46267 | K73: 1298.74 | L73: 1298.74 | M73: =IF(L73>2500, "High Sales", "Low Sales") -> Low Sales | N73: =IF(OR(ISBLANK(L73), L73="", L73=0), "Grade C", IF(L73>=4000, "Grade A", IF(L73>=2000, "Grade B", "Grade C"))) -> Grade C | O73: 20 | P73: 20 | Q73: Delivered | R73: 12 | S73: =CONCATENATE(OrdersTable[[#This Row],[Clean_ID]],"-",OrdersTable[[#This Row],[Clean_Region]],"-",OrdersTable[[#This Row],[Clean_Product]]) -> 1071-WEST-Office Supplies
A74: ORD1072 | B74: =RIGHT(A74, 4) -> 1072 | C74: Amanda Welch | D74: =PROPER(TRIM(C74)) -> Amanda Welch | E74: Central | F74: =UPPER(TRIM(E74)) -> CENTRAL | G74: Electronics | H74: =PROPER(TRIM(G74)) -> Electronics | I74: 2024-12-24 | J74: 45650 | K74: 3268.21 | L74: 3268.21 | M74: =IF(L74>2500, "High Sales", "Low Sales") -> High Sales | N74: =IF(OR(ISBLANK(L74), L74="", L74=0), "Grade C", IF(L74>=4000, "Grade A", IF(L74>=2000, "Grade B", "Grade C"))) -> Grade B | O74: 5 | P74: 5 | Q74: Pending | R74: 4 | S74: =CONCATENATE(OrdersTable[[#This Row],[Clean_ID]],"-",OrdersTable[[#This Row],[Clean_Region]],"-",OrdersTable[[#This Row],[Clean_Product]]) -> 1072-CENTRAL-Electronics
A75: ORD1073 | B75: =RIGHT(A75, 4) -> 1073 | C75: Dr. Scott Thompson | D75: =PROPER(TRIM(C75)) -> Dr. Scott Thompson | E75: North | F75: =UPPER(TRIM(E75)) -> NORTH | G75: Furniture | H75: =PROPER(TRIM(G75)) -> Furniture | I75: 2024-09-01 | J75: 45536 | K75: 2394.13 | L75: 2394.13 | M75: =IF(L75>2500, "High Sales", "Low Sales") -> Low Sales | N75: =IF(OR(ISBLANK(L75), L75="", L75=0), "Grade C", IF(L75>=4000, "Grade A", IF(L75>=2000, "Grade B", "Grade C"))) -> Grade B | P75: 0 | Q75: Pending | R75: 8 | S75: =CONCATENATE(OrdersTable[[#This Row],[Clean_ID]],"-",OrdersTable[[#This Row],[Clean_Region]],"-",OrdersTable[[#This Row],[Clean_Product]]) -> 1073-NORTH-Furniture
A76: ORD1074 | B76: =RIGHT(A76, 4) -> 1074 | C76: Jennifer Reed | D76: =PROPER(TRIM(C76)) -> Jennifer Reed | E76: north | F76: =UPPER(TRIM(E76)) -> NORTH | G76: Office Supplies | H76: =PROPER(TRIM(G76)) -> Office Supplies | I76: 24/02/2026 | J76: 46077 | K76: 880.56 | L76: 880.56 | M76: =IF(L76>2500, "High Sales", "Low Sales") -> Low Sales | N76: =IF(OR(ISBLANK(L76), L76="", L76=0), "Grade C", IF(L76>=4000, "Grade A", IF(L76>=2000, "Grade B", "Grade C"))) -> Grade C | O76: 10 | P76: 10 | Q76: Cancelled | R76: 2 | S76: =CONCATENATE(OrdersTable[[#This Row],[Clean_ID]],"-",OrdersTable[[#This Row],[Clean_Region]],"-",OrdersTable[[#This Row],[Clean_Product]]) -> 1074-NORTH-Office Supplies
A77: ORD1075 | B77: =RIGHT(A77, 4) -> 1075 | C77: Jennifer Gonzalez | D77: =PROPER(TRIM(C77)) -> Jennifer Gonzalez | E77: Central | F77: =UPPER(TRIM(E77)) -> CENTRAL | G77: Electronics | H77: =PROPER(TRIM(G77)) -> Electronics | I77: 11-15-2024 | J77: 45611 | L77: 0 | M77: =IF(L77>2500, "High Sales", "Low Sales") -> Low Sales | N77: =IF(OR(ISBLANK(L77), L77="", L77=0), "Grade C", IF(L77>=4000, "Grade A", IF(L77>=2000, "Grade B", "Grade C"))) -> Grade C | O77: 20 | P77: 20 | Q77: Pending | R77: 2 | S77: =CONCATENATE(OrdersTable[[#This Row],[Clean_ID]],"-",OrdersTable[[#This Row],[Clean_Region]],"-",OrdersTable[[#This Row],[Clean_Product]]) -> 1075-CENTRAL-Electronics
A78: ORD1076 | B78: =RIGHT(A78, 4) -> 1076 | C78: Charles Nichols | D78: =PROPER(TRIM(C78)) -> Charles Nichols | E78: Central | F78: =UPPER(TRIM(E78)) -> CENTRAL | G78: Furniture | H78: =PROPER(TRIM(G78)) -> Furniture | I78: 04-14-2024 | J78: 45396 | K78: 3873.78 | L78: 3873.78 | M78: =IF(L78>2500, "High Sales", "Low Sales") -> High Sales | N78: =IF(OR(ISBLANK(L78), L78="", L78=0), "Grade C", IF(L78>=4000, "Grade A", IF(L78>=2000, "Grade B", "Grade C"))) -> Grade B | P78: 0 | Q78: Delivered | R78: 6 | S78: =CONCATENATE(OrdersTable[[#This Row],[Clean_ID]],"-",OrdersTable[[#This Row],[Clean_Region]],"-",OrdersTable[[#This Row],[Clean_Product]]) -> 1076-CENTRAL-Furniture
A79: ORD1077 | B79: =RIGHT(A79, 4) -> 1077 | C79: Kristine House | D79: =PROPER(TRIM(C79)) -> Kristine House | E79: Central | F79: =UPPER(TRIM(E79)) -> CENTRAL | G79: electronics | H79: =PROPER(TRIM(G79)) -> Electronics | I79: 08/11/2025 | J79: 45880 | L79: 0 | M79: =IF(L79>2500, "High Sales", "Low Sales") -> Low Sales | N79: =IF(OR(ISBLANK(L79), L79="", L79=0), "Grade C", IF(L79>=4000, "Grade A", IF(L79>=2000, "Grade B", "Grade C"))) -> Grade C | O79: 5 | P79: 5 | Q79: Shipped | R79: 14 | S79: =CONCATENATE(OrdersTable[[#This Row],[Clean_ID]],"-",OrdersTable[[#This Row],[Clean_Region]],"-",OrdersTable[[#This Row],[Clean_Product]]) -> 1077-CENTRAL-Electronics
A80: ORD1078 | B80: =RIGHT(A80, 4) -> 1078 | C80: Mrs. Julia Tyler | D80: =PROPER(TRIM(C80)) -> Mrs. Julia Tyler | E80: West | F80: =UPPER(TRIM(E80)) -> WEST | G80: Electronics | H80: =PROPER(TRIM(G80)) -> Electronics | I80: 19/03/2025 | J80: 45735 | L80: 0 | M80: =IF(L80>2500, "High Sales", "Low Sales") -> Low Sales | N80: =IF(OR(ISBLANK(L80), L80="", L80=0), "Grade C", IF(L80>=4000, "Grade A", IF(L80>=2000, "Grade B", "Grade C"))) -> Grade C | O80: 10 | P80: 10 | Q80: Shipped | R80: 3 | S80: =CONCATENATE(OrdersTable[[#This Row],[Clean_ID]],"-",OrdersTable[[#This Row],[Clean_Region]],"-",OrdersTable[[#This Row],[Clean_Product]]) -> 1078-WEST-Electronics
A81: ORD1079 | B81: =RIGHT(A81, 4) -> 1079 | C81: Dawn Hanson | D81: =PROPER(TRIM(C81)) -> Dawn Hanson | E81: north | F81: =UPPER(TRIM(E81)) -> NORTH | G81: Office Supplies | H81: =PROPER(TRIM(G81)) -> Office Supplies | I81: 09-22-2025 | J81: 45922 | L81: 0 | M81: =IF(L81>2500, "High Sales", "Low Sales") -> Low Sales | N81: =IF(OR(ISBLANK(L81), L81="", L81=0), "Grade C", IF(L81>=4000, "Grade A", IF(L81>=2000, "Grade B", "Grade C"))) -> Grade C | O81: 20 | P81: 20 | Q81: Returned | R81: 5 | S81: =CONCATENATE(OrdersTable[[#This Row],[Clean_ID]],"-",OrdersTable[[#This Row],[Clean_Region]],"-",OrdersTable[[#This Row],[Clean_Product]]) -> 1079-NORTH-Office Supplies
A82: ORD1080 | B82: =RIGHT(A82, 4) -> 1080 | C82: Stanley Martinez | D82: =PROPER(TRIM(C82)) -> Stanley Martinez | E82: East | F82: =UPPER(TRIM(E82)) -> EAST | G82: Furniture | H82: =PROPER(TRIM(G82)) -> Furniture | I82: 2026-04-30 | J82: 46142 | L82: 0 | M82: =IF(L82>2500, "High Sales", "Low Sales") -> Low Sales | N82: =IF(OR(ISBLANK(L82), L82="", L82=0), "Grade C", IF(L82>=4000, "Grade A", IF(L82>=2000, "Grade B", "Grade C"))) -> Grade C | O82: 10 | P82: 10 | Q82: Shipped | R82: 10 | S82: =CONCATENATE(OrdersTable[[#This Row],[Clean_ID]],"-",OrdersTable[[#This Row],[Clean_Region]],"-",OrdersTable[[#This Row],[Clean_Product]]) -> 1080-EAST-Furniture
A83: ORD1081 | B83: =RIGHT(A83, 4) -> 1081 | C83: Theodore Johnson | D83: =PROPER(TRIM(C83)) -> Theodore Johnson | E83: Central | F83: =UPPER(TRIM(E83)) -> CENTRAL | G83: electronics | H83: =PROPER(TRIM(G83)) -> Electronics | I83: 2024-12-10 | J83: 45636 | L83: 0 | M83: =IF(L83>2500, "High Sales", "Low Sales") -> Low Sales | N83: =IF(OR(ISBLANK(L83), L83="", L83=0), "Grade C", IF(L83>=4000, "Grade A", IF(L83>=2000, "Grade B", "Grade C"))) -> Grade C | O83: 10 | P83: 10 | Q83: Shipped | R83: 4 | S83: =CONCATENATE(OrdersTable[[#This Row],[Clean_ID]],"-",OrdersTable[[#This Row],[Clean_Region]],"-",OrdersTable[[#This Row],[Clean_Product]]) -> 1081-CENTRAL-Electronics
A84: ORD1082 | B84: =RIGHT(A84, 4) -> 1082 | C84: James Parsons | D84: =PROPER(TRIM(C84)) -> James Parsons | E84: East | F84: =UPPER(TRIM(E84)) -> EAST | G84: Office Supplies | H84: =PROPER(TRIM(G84)) -> Office Supplies | I84: 14/12/2024 | J84: 45640 | L84: 0 | M84: =IF(L84>2500, "High Sales", "Low Sales") -> Low Sales | N84: =IF(OR(ISBLANK(L84), L84="", L84=0), "Grade C", IF(L84>=4000, "Grade A", IF(L84>=2000, "Grade B", "Grade C"))) -> Grade C | P84: 0 | Q84: Delivered | R84: 9 | S84: =CONCATENATE(OrdersTable[[#This Row],[Clean_ID]],"-",OrdersTable[[#This Row],[Clean_Region]],"-",OrdersTable[[#This Row],[Clean_Product]]) -> 1082-EAST-Office Supplies
A85: ORD1083 | B85: =RIGHT(A85, 4) -> 1083 | C85: Kimberly Williams MD | D85: =PROPER(TRIM(C85)) -> Kimberly Williams Md | E85: South | F85: =UPPER(TRIM(E85)) -> SOUTH | G85: Electronics | H85: =PROPER(TRIM(G85)) -> Electronics | I85: 09-04-2024 | J85: 45539 | K85: 2061.82 | L85: 2061.82 | M85: =IF(L85>2500, "High Sales", "Low Sales") -> Low Sales | N85: =IF(OR(ISBLANK(L85), L85="", L85=0), "Grade C", IF(L85>=4000, "Grade A", IF(L85>=2000, "Grade B", "Grade C"))) -> Grade B | O85: 20 | P85: 20 | Q85: Shipped | R85: 8 | S85: =CONCATENATE(OrdersTable[[#This Row],[Clean_ID]],"-",OrdersTable[[#This Row],[Clean_Region]],"-",OrdersTable[[#This Row],[Clean_Product]]) -> 1083-SOUTH-Electronics
A86: ORD1084 | B86: =RIGHT(A86, 4) -> 1084 | C86: Manuel Ramirez | D86: =PROPER(TRIM(C86)) -> Manuel Ramirez | E86: North | F86: =UPPER(TRIM(E86)) -> NORTH | G86: Electronics | H86: =PROPER(TRIM(G86)) -> Electronics | I86: 2024-10-28 | J86: 45593 | K86: 2051.79 | L86: 2051.79 | M86: =IF(L86>2500, "High Sales", "Low Sales") -> Low Sales | N86: =IF(OR(ISBLANK(L86), L86="", L86=0), "Grade C", IF(L86>=4000, "Grade A", IF(L86>=2000, "Grade B", "Grade C"))) -> Grade B | O86: 15 | P86: 15 | Q86: Returned | R86: 6 | S86: =CONCATENATE(OrdersTable[[#This Row],[Clean_ID]],"-",OrdersTable[[#This Row],[Clean_Region]],"-",OrdersTable[[#This Row],[Clean_Product]]) -> 1084-NORTH-Electronics
A87: ORD1085 | B87: =RIGHT(A87, 4) -> 1085 | C87: Daniel Rhodes | D87: =PROPER(TRIM(C87)) -> Daniel Rhodes | E87: West | F87: =UPPER(TRIM(E87)) -> WEST | G87: Office Supplies | H87: =PROPER(TRIM(G87)) -> Office Supplies | I87: 03-11-2025 | J87: 45727 | L87: 0 | M87: =IF(L87>2500, "High Sales", "Low Sales") -> Low Sales | N87: =IF(OR(ISBLANK(L87), L87="", L87=0), "Grade C", IF(L87>=4000, "Grade A", IF(L87>=2000, "Grade B", "Grade C"))) -> Grade C | O87: 20 | P87: 20 | Q87: Cancelled | R87: 5 | S87: =CONCATENATE(OrdersTable[[#This Row],[Clean_ID]],"-",OrdersTable[[#This Row],[Clean_Region]],"-",OrdersTable[[#This Row],[Clean_Product]]) -> 1085-WEST-Office Supplies
A88: ORD1086 | B88: =RIGHT(A88, 4) -> 1086 | C88: Corey Fischer | D88: =PROPER(TRIM(C88)) -> Corey Fischer | E88: East | F88: =UPPER(TRIM(E88)) -> EAST | G88: Furniture | H88: =PROPER(TRIM(G88)) -> Furniture | I88: 05-03-2024 | J88: 45415 | K88: 1003.29 | L88: 1003.29 | M88: =IF(L88>2500, "High Sales", "Low Sales") -> Low Sales | N88: =IF(OR(ISBLANK(L88), L88="", L88=0), "Grade C", IF(L88>=4000, "Grade A", IF(L88>=2000, "Grade B", "Grade C"))) -> Grade C | P88: 0 | Q88: Pending | R88: 4 | S88: =CONCATENATE(OrdersTable[[#This Row],[Clean_ID]],"-",OrdersTable[[#This Row],[Clean_Region]],"-",OrdersTable[[#This Row],[Clean_Product]]) -> 1086-EAST-Furniture
A89: ORD1087 | B89: =RIGHT(A89, 4) -> 1087 | C89: Roger Yates | D89: =PROPER(TRIM(C89)) -> Roger Yates | E89: South | F89: =UPPER(TRIM(E89)) -> SOUTH | G89: electronics | H89: =PROPER(TRIM(G89)) -> Electronics | I89: 10-10-2024 | J89: 45575 | L89: 0 | M89: =IF(L89>2500, "High Sales", "Low Sales") -> Low Sales | N89: =IF(OR(ISBLANK(L89), L89="", L89=0), "Grade C", IF(L89>=4000, "Grade A", IF(L89>=2000, "Grade B", "Grade C"))) -> Grade C | O89: 5 | P89: 5 | Q89: Pending | R89: 5 | S89: =CONCATENATE(OrdersTable[[#This Row],[Clean_ID]],"-",OrdersTable[[#This Row],[Clean_Region]],"-",OrdersTable[[#This Row],[Clean_Product]]) -> 1087-SOUTH-Electronics
A90: ORD1088 | B90: =RIGHT(A90, 4) -> 1088 | C90: Mr. James Cannon | D90: =PROPER(TRIM(C90)) -> Mr. James Cannon | E90: South | F90: =UPPER(TRIM(E90)) -> SOUTH | G90: Office Supplies | H90: =PROPER(TRIM(G90)) -> Office Supplies | I90: 02/07/2024 | J90: 45329 | K90: 120.03 | L90: 120.03 | M90: =IF(L90>2500, "High Sales", "Low Sales") -> Low Sales | N90: =IF(OR(ISBLANK(L90), L90="", L90=0), "Grade C", IF(L90>=4000, "Grade A", IF(L90>=2000, "Grade B", "Grade C"))) -> Grade C | O90: 15 | P90: 15 | Q90: Delivered | R90: 1 | S90: =CONCATENATE(OrdersTable[[#This Row],[Clean_ID]],"-",OrdersTable[[#This Row],[Clean_Region]],"-",OrdersTable[[#This Row],[Clean_Product]]) -> 1088-SOUTH-Office Supplies
A91: ORD1089 | B91: =RIGHT(A91, 4) -> 1089 | C91: Thomas Montes | D91: =PROPER(TRIM(C91)) -> Thomas Montes | E91: Central | F91: =UPPER(TRIM(E91)) -> CENTRAL | G91: Office Supplies | H91: =PROPER(TRIM(G91)) -> Office Supplies | I91: 2025-12-15 | J91: 46006 | L91: 0 | M91: =IF(L91>2500, "High Sales", "Low Sales") -> Low Sales | N91: =IF(OR(ISBLANK(L91), L91="", L91=0), "Grade C", IF(L91>=4000, "Grade A", IF(L91>=2000, "Grade B", "Grade C"))) -> Grade C | O91: 5 | P91: 5 | Q91: Delivered | R91: 10 | S91: =CONCATENATE(OrdersTable[[#This Row],[Clean_ID]],"-",OrdersTable[[#This Row],[Clean_Region]],"-",OrdersTable[[#This Row],[Clean_Product]]) -> 1089-CENTRAL-Office Supplies
A92: ORD1090 | B92: =RIGHT(A92, 4) -> 1090 | C92: Daniel Villanueva | D92: =PROPER(TRIM(C92)) -> Daniel Villanueva | E92: East | F92: =UPPER(TRIM(E92)) -> EAST | G92: electronics | H92: =PROPER(TRIM(G92)) -> Electronics | I92: 05/05/2025 | J92: 45782 | K92: 1736.49 | L92: 1736.49 | M92: =IF(L92>2500, "High Sales", "Low Sales") -> Low Sales | N92: =IF(OR(ISBLANK(L92), L92="", L92=0), "Grade C", IF(L92>=4000, "Grade A", IF(L92>=2000, "Grade B", "Grade C"))) -> Grade C | O92: 15 | P92: 15 | Q92: Shipped | R92: 2 | S92: =CONCATENATE(OrdersTable[[#This Row],[Clean_ID]],"-",OrdersTable[[#This Row],[Clean_Region]],"-",OrdersTable[[#This Row],[Clean_Product]]) -> 1090-EAST-Electronics
A93: ORD1091 | B93: =RIGHT(A93, 4) -> 1091 | C93: Katherine Thomas | D93: =PROPER(TRIM(C93)) -> Katherine Thomas | E93: North | F93: =UPPER(TRIM(E93)) -> NORTH | G93: electronics | H93: =PROPER(TRIM(G93)) -> Electronics | I93: 2025-05-18 | J93: 45795 | K93: 2906.25 | L93: 2906.25 | M93: =IF(L93>2500, "High Sales", "Low Sales") -> High Sales | N93: =IF(OR(ISBLANK(L93), L93="", L93=0), "Grade C", IF(L93>=4000, "Grade A", IF(L93>=2000, "Grade B", "Grade C"))) -> Grade B | O93: 10 | P93: 10 | Q93: Pending | R93: 13 | S93: =CONCATENATE(OrdersTable[[#This Row],[Clean_ID]],"-",OrdersTable[[#This Row],[Clean_Region]],"-",OrdersTable[[#This Row],[Clean_Product]]) -> 1091-NORTH-Electronics
A94: ORD1092 | B94: =RIGHT(A94, 4) -> 1092 | C94: Jennifer Sanders | D94: =PROPER(TRIM(C94)) -> Jennifer Sanders | E94: Central | F94: =UPPER(TRIM(E94)) -> CENTRAL | G94: Office Supplies | H94: =PROPER(TRIM(G94)) -> Office Supplies | I94: 2024-03-28 | J94: 45379 | L94: 0 | M94: =IF(L94>2500, "High Sales", "Low Sales") -> Low Sales | N94: =IF(OR(ISBLANK(L94), L94="", L94=0), "Grade C", IF(L94>=4000, "Grade A", IF(L94>=2000, "Grade B", "Grade C"))) -> Grade C | P94: 0 | Q94: Returned | R94: 13 | S94: =CONCATENATE(OrdersTable[[#This Row],[Clean_ID]],"-",OrdersTable[[#This Row],[Clean_Region]],"-",OrdersTable[[#This Row],[Clean_Product]]) -> 1092-CENTRAL-Office Supplies
A95: ORD1093 | B95: =RIGHT(A95, 4) -> 1093 | C95: Susan Thompson | D95: =PROPER(TRIM(C95)) -> Susan Thompson | E95: Central | F95: =UPPER(TRIM(E95)) -> CENTRAL | G95: Furniture | H95: =PROPER(TRIM(G95)) -> Furniture | I95: 03-05-2026 | J95: 46086 | L95: 0 | M95: =IF(L95>2500, "High Sales", "Low Sales") -> Low Sales | N95: =IF(OR(ISBLANK(L95), L95="", L95=0), "Grade C", IF(L95>=4000, "Grade A", IF(L95>=2000, "Grade B", "Grade C"))) -> Grade C | O95: 15 | P95: 15 | Q95: Returned | R95: 7 | S95: =CONCATENATE(OrdersTable[[#This Row],[Clean_ID]],"-",OrdersTable[[#This Row],[Clean_Region]],"-",OrdersTable[[#This Row],[Clean_Product]]) -> 1093-CENTRAL-Furniture
A96: ORD1094 | B96: =RIGHT(A96, 4) -> 1094 | C96: Travis Coleman | D96: =PROPER(TRIM(C96)) -> Travis Coleman | E96: East | F96: =UPPER(TRIM(E96)) -> EAST | G96: Electronics | H96: =PROPER(TRIM(G96)) -> Electronics | I96: 09-16-2025 | J96: 45916 | K96: 541.21 | L96: 541.21 | M96: =IF(L96>2500, "High Sales", "Low Sales") -> Low Sales | N96: =IF(OR(ISBLANK(L96), L96="", L96=0), "Grade C", IF(L96>=4000, "Grade A", IF(L96>=2000, "Grade B", "Grade C"))) -> Grade C | O96: 10 | P96: 10 | Q96: Cancelled | R96: 11 | S96: =CONCATENATE(OrdersTable[[#This Row],[Clean_ID]],"-",OrdersTable[[#This Row],[Clean_Region]],"-",OrdersTable[[#This Row],[Clean_Product]]) -> 1094-EAST-Electronics
A97: ORD1095 | B97: =RIGHT(A97, 4) -> 1095 | C97: Steven Davis | D97: =PROPER(TRIM(C97)) -> Steven Davis | E97: North | F97: =UPPER(TRIM(E97)) -> NORTH | G97: Furniture | H97: =PROPER(TRIM(G97)) -> Furniture | I97: 2024-09-02 | J97: 45537 | K97: 2782.36 | L97: 2782.36 | M97: =IF(L97>2500, "High Sales", "Low Sales") -> High Sales | N97: =IF(OR(ISBLANK(L97), L97="", L97=0), "Grade C", IF(L97>=4000, "Grade A", IF(L97>=2000, "Grade B", "Grade C"))) -> Grade B | O97: 5 | P97: 5 | Q97: Shipped | R97: 8 | S97: =CONCATENATE(OrdersTable[[#This Row],[Clean_ID]],"-",OrdersTable[[#This Row],[Clean_Region]],"-",OrdersTable[[#This Row],[Clean_Product]]) -> 1095-NORTH-Furniture
A98: ORD1096 | B98: =RIGHT(A98, 4) -> 1096 | C98: Dean Shelton | D98: =PROPER(TRIM(C98)) -> Dean Shelton | E98: north | F98: =UPPER(TRIM(E98)) -> NORTH | G98: electronics | H98: =PROPER(TRIM(G98)) -> Electronics | I98: 2024-10-25 | J98: 45590 | L98: 0 | M98: =IF(L98>2500, "High Sales", "Low Sales") -> Low Sales | N98: =IF(OR(ISBLANK(L98), L98="", L98=0), "Grade C", IF(L98>=4000, "Grade A", IF(L98>=2000, "Grade B", "Grade C"))) -> Grade C | O98: 20 | P98: 20 | Q98: Delivered | R98: 11 | S98: =CONCATENATE(OrdersTable[[#This Row],[Clean_ID]],"-",OrdersTable[[#This Row],[Clean_Region]],"-",OrdersTable[[#This Row],[Clean_Product]]) -> 1096-NORTH-Electronics
A99: ORD1097 | B99: =RIGHT(A99, 4) -> 1097 | C99: Gabriel Bell | D99: =PROPER(TRIM(C99)) -> Gabriel Bell | E99: South | F99: =UPPER(TRIM(E99)) -> SOUTH | G99: Office Supplies | H99: =PROPER(TRIM(G99)) -> Office Supplies | I99: 03-17-2026 | J99: 46098 | K99: 2969.46 | L99: 2969.46 | M99: =IF(L99>2500, "High Sales", "Low Sales") -> High Sales | N99: =IF(OR(ISBLANK(L99), L99="", L99=0), "Grade C", IF(L99>=4000, "Grade A", IF(L99>=2000, "Grade B", "Grade C"))) -> Grade B | O99: 20 | P99: 20 | Q99: Delivered | R99: 9 | S99: =CONCATENATE(OrdersTable[[#This Row],[Clean_ID]],"-",OrdersTable[[#This Row],[Clean_Region]],"-",OrdersTable[[#This Row],[Clean_Product]]) -> 1097-SOUTH-Office Supplies
A100: ORD1098 | B100: =RIGHT(A100, 4) -> 1098 | C100: Jaclyn Martinez | D100: =PROPER(TRIM(C100)) -> Jaclyn Martinez | E100: South | F100: =UPPER(TRIM(E100)) -> SOUTH | G100: Furniture | H100: =PROPER(TRIM(G100)) -> Furniture | I100: 2024-09-29 | J100: 45564 | K100: 403.48 | L100: 403.48 | M100: =IF(L100>2500, "High Sales", "Low Sales") -> Low Sales | N100: =IF(OR(ISBLANK(L100), L100="", L100=0), "Grade C", IF(L100>=4000, "Grade A", IF(L100>=2000, "Grade B", "Grade C"))) -> Grade C | O100: 15 | P100: 15 | Q100: Returned | R100: 12 | S100: =CONCATENATE(OrdersTable[[#This Row],[Clean_ID]],"-",OrdersTable[[#This Row],[Clean_Region]],"-",OrdersTable[[#This Row],[Clean_Product]]) -> 1098-SOUTH-Furniture
...

Sheet Inventory
A1: Product_ID | B1: Product_Name | C1: Clean_Name | D1: Warehouse | E1: Clean_Warehouse | F1: Stock_Qty | G1: Clean_Stock | H1: Reorder_Level | I1: Unit_Cost | J1: Supplier_ID | K1: Inventory_Status | N1: Matching products with warehouses
A2: PRD1 | B2: Man | C2: =PROPER(TRIM(B2)) -> Man | D2: WH-B | E2: =PROPER(TRIM(D2)) -> Wh-B | G2: 0 | H2: 189 | I2: 222.48 | J2: SUP67 | K2: =IF(OR(ISBLANK(G2), G2<=H2), "Low Stock - Reorder", "Healthy Stock") -> Low Stock - Reorder | N2: =INDEX(Inventory!D:D, MATCH(A12, Inventory!A:A, 0)) -> WH-C
A3: PRD2 | B3: Sport | C3: =PROPER(TRIM(B3)) -> Sport | D3: WH-C | E3: =PROPER(TRIM(D3)) -> Wh-C | G3: 0 | H3: 104 | I3: 199.5 | J3: SUP10 | K3: =IF(OR(ISBLANK(G3), G3<=H3), "Low Stock - Reorder", "Healthy Stock") -> Low Stock - Reorder
A4: PRD3 | B4: Financial | C4: =PROPER(TRIM(B4)) -> Financial | D4: wh-a | E4: =PROPER(TRIM(D4)) -> Wh-A | F4: 207 | G4: 207 | H4: 54 | I4: 426.71 | J4: SUP38 | K4: =IF(OR(ISBLANK(G4), G4<=H4), "Low Stock - Reorder", "Healthy Stock") -> Healthy Stock
A5: PRD4 | B5: Final | C5: =PROPER(TRIM(B5)) -> Final | D5: wh-a | E5: =PROPER(TRIM(D5)) -> Wh-A | F5: 42 | G5: 42 | H5: 170 | I5: 83.06 | J5: SUP51 | K5: =IF(OR(ISBLANK(G5), G5<=H5), "Low Stock - Reorder", "Healthy Stock") -> Low Stock - Reorder
A6: PRD5 | B6: Course | C6: =PROPER(TRIM(B6)) -> Course | D6: WH-B | E6: =PROPER(TRIM(D6)) -> Wh-B | F6: 526 | G6: 526 | H6: 110 | I6: 472.62 | J6: SUP90 | K6: =IF(OR(ISBLANK(G6), G6<=H6), "Low Stock - Reorder", "Healthy Stock") -> Healthy Stock
A7: PRD6 | B7: Page | C7: =PROPER(TRIM(B7)) -> Page | D7: wh-a | E7: =PROPER(TRIM(D7)) -> Wh-A | F7: 319 | G7: 319 | H7: 181 | I7: 413.56 | J7: SUP37 | K7: =IF(OR(ISBLANK(G7), G7<=H7), "Low Stock - Reorder", "Healthy Stock") -> Healthy Stock
A8: PRD7 | B8: Course | C8: =PROPER(TRIM(B8)) -> Course | D8: wh-a | E8: =PROPER(TRIM(D8)) -> Wh-A | F8: 288 | G8: 288 | H8: 73 | I8: 219.39 | J8: SUP31 | K8: =IF(OR(ISBLANK(G8), G8<=H8), "Low Stock - Reorder", "Healthy Stock") -> Healthy Stock
A9: PRD8 | B9: Address | C9: =PROPER(TRIM(B9)) -> Address | D9: WH-C | E9: =PROPER(TRIM(D9)) -> Wh-C | F9: 873 | G9: 873 | H9: 58 | I9: 118.23 | J9: SUP13 | K9: =IF(OR(ISBLANK(G9), G9<=H9), "Low Stock - Reorder", "Healthy Stock") -> Healthy Stock
A10: PRD9 | B10: Seem | C10: =PROPER(TRIM(B10)) -> Seem | D10: WH-A | E10: =PROPER(TRIM(D10)) -> Wh-A | F10: 730 | G10: 730 | H10: 149 | I10: 208.96 | J10: SUP99 | K10: =IF(OR(ISBLANK(G10), G10<=H10), "Low Stock - Reorder", "Healthy Stock") -> Healthy Stock
A11: PRD10 | B11: Street | C11: =PROPER(TRIM(B11)) -> Street | D11: wh-a | E11: =PROPER(TRIM(D11)) -> Wh-A | F11: 441 | G11: 441 | H11: 86 | I11: 264.46 | J11: SUP47 | K11: =IF(OR(ISBLANK(G11), G11<=H11), "Low Stock - Reorder", "Healthy Stock") -> Healthy Stock
A12: PRD11 | B12: Music | C12: =PROPER(TRIM(B12)) -> Music | D12: WH-C | E12: =PROPER(TRIM(D12)) -> Wh-C | F12: 313 | G12: 313 | H12: 124 | I12: 376.31 | J12: SUP69 | K12: =IF(OR(ISBLANK(G12), G12<=H12), "Low Stock - Reorder", "Healthy Stock") -> Healthy Stock
A13: PRD12 | B13: Involve | C13: =PROPER(TRIM(B13)) -> Involve | D13: WH-C | E13: =PROPER(TRIM(D13)) -> Wh-C | G13: 0 | H13: 88 | I13: 85.61 | J13: SUP74 | K13: =IF(OR(ISBLANK(G13), G13<=H13), "Low Stock - Reorder", "Healthy Stock") -> Low Stock - Reorder
A14: PRD13 | B14: Idea | C14: =PROPER(TRIM(B14)) -> Idea | D14: WH-C | E14: =PROPER(TRIM(D14)) -> Wh-C | F14: Unknown | G14: 0 | H14: 50 | I14: 258.17 | J14: SUP68 | K14: =IF(OR(ISBLANK(G14), G14<=H14), "Low Stock - Reorder", "Healthy Stock") -> Low Stock - Reorder
A15: PRD14 | B15: Beat | C15: =PROPER(TRIM(B15)) -> Beat | D15: wh-a | E15: =PROPER(TRIM(D15)) -> Wh-A | F15: 81 | G15: 81 | H15: 147 | I15: 366.9 | J15: SUP100 | K15: =IF(OR(ISBLANK(G15), G15<=H15), "Low Stock - Reorder", "Healthy Stock") -> Low Stock - Reorder
A16: PRD15 | B16: Whether | C16: =PROPER(TRIM(B16)) -> Whether | D16: wh-a | E16: =PROPER(TRIM(D16)) -> Wh-A | F16: 765 | G16: 765 | H16: 65 | I16: 95.41 | J16: SUP50 | K16: =IF(OR(ISBLANK(G16), G16<=H16), "Low Stock - Reorder", "Healthy Stock") -> Healthy Stock
A17: PRD16 | B17: Speech | C17: =PROPER(TRIM(B17)) -> Speech | D17: WH-A | E17: =PROPER(TRIM(D17)) -> Wh-A | G17: 0 | H17: 54 | I17: 320.39 | J17: SUP57 | K17: =IF(OR(ISBLANK(G17), G17<=H17), "Low Stock - Reorder", "Healthy Stock") -> Low Stock - Reorder
A18: PRD17 | B18: Recently | C18: =PROPER(TRIM(B18)) -> Recently | D18: WH-C | E18: =PROPER(TRIM(D18)) -> Wh-C | G18: 0 | H18: 101 | I18: 258 | J18: SUP82 | K18: =IF(OR(ISBLANK(G18), G18<=H18), "Low Stock - Reorder", "Healthy Stock") -> Low Stock - Reorder
A19: PRD18 | B19: Call | C19: =PROPER(TRIM(B19)) -> Call | D19: WH-A | E19: =PROPER(TRIM(D19)) -> Wh-A | G19: 0 | H19: 84 | I19: 451.25 | J19: SUP36 | K19: =IF(OR(ISBLANK(G19), G19<=H19), "Low Stock - Reorder", "Healthy Stock") -> Low Stock - Reorder
A20: PRD19 | B20: Character | C20: =PROPER(TRIM(B20)) -> Character | D20: WH-A | E20: =PROPER(TRIM(D20)) -> Wh-A | F20: 987 | G20: 987 | H20: 156 | I20: 197.49 | J20: SUP63 | K20: =IF(OR(ISBLANK(G20), G20<=H20), "Low Stock - Reorder", "Healthy Stock") -> Healthy Stock
A21: PRD20 | B21: Street | C21: =PROPER(TRIM(B21)) -> Street | D21: WH-C | E21: =PROPER(TRIM(D21)) -> Wh-C | G21: 0 | H21: 106 | I21: 424.94 | J21: SUP19 | K21: =IF(OR(ISBLANK(G21), G21<=H21), "Low Stock - Reorder", "Healthy Stock") -> Low Stock - Reorder
A22: PRD21 | B22: Tonight | C22: =PROPER(TRIM(B22)) -> Tonight | D22: WH-A | E22: =PROPER(TRIM(D22)) -> Wh-A | G22: 0 | H22: 64 | I22: 438.05 | J22: SUP88 | K22: =IF(OR(ISBLANK(G22), G22<=H22), "Low Stock - Reorder", "Healthy Stock") -> Low Stock - Reorder
A23: PRD22 | B23: Third | C23: =PROPER(TRIM(B23)) -> Third | D23: WH-C | E23: =PROPER(TRIM(D23)) -> Wh-C | F23: 156 | G23: 156 | H23: 184 | I23: 288.26 | J23: SUP45 | K23: =IF(OR(ISBLANK(G23), G23<=H23), "Low Stock - Reorder", "Healthy Stock") -> Low Stock - Reorder
A24: PRD23 | B24: Nice | C24: =PROPER(TRIM(B24)) -> Nice | D24: WH-C | E24: =PROPER(TRIM(D24)) -> Wh-C | G24: 0 | H24: 53 | I24: 233.15 | J24: SUP9 | K24: =IF(OR(ISBLANK(G24), G24<=H24), "Low Stock - Reorder", "Healthy Stock") -> Low Stock - Reorder
A25: PRD24 | B25: Same | C25: =PROPER(TRIM(B25)) -> Same | D25: WH-A | E25: =PROPER(TRIM(D25)) -> Wh-A | G25: 0 | H25: 93 | I25: 310.19 | J25: SUP48 | K25: =IF(OR(ISBLANK(G25), G25<=H25), "Low Stock - Reorder", "Healthy Stock") -> Low Stock - Reorder
A26: PRD25 | B26: Newspaper | C26: =PROPER(TRIM(B26)) -> Newspaper | D26: WH-A | E26: =PROPER(TRIM(D26)) -> Wh-A | F26: 172 | G26: 172 | H26: 56 | I26: 495.28 | J26: SUP82 | K26: =IF(OR(ISBLANK(G26), G26<=H26), "Low Stock - Reorder", "Healthy Stock") -> Healthy Stock
A27: PRD26 | B27: Surface | C27: =PROPER(TRIM(B27)) -> Surface | D27: WH-A | E27: =PROPER(TRIM(D27)) -> Wh-A | G27: 0 | H27: 161 | I27: 225.03 | J27: SUP33 | K27: =IF(OR(ISBLANK(G27), G27<=H27), "Low Stock - Reorder", "Healthy Stock") -> Low Stock - Reorder
A28: PRD27 | B28: Everybody | C28: =PROPER(TRIM(B28)) -> Everybody | D28: WH-C | E28: =PROPER(TRIM(D28)) -> Wh-C | F28: 239 | G28: 239 | H28: 100 | I28: 389.22 | J28: SUP64 | K28: =IF(OR(ISBLANK(G28), G28<=H28), "Low Stock - Reorder", "Healthy Stock") -> Healthy Stock
A29: PRD28 | B29: Maintain | C29: =PROPER(TRIM(B29)) -> Maintain | D29: WH-A | E29: =PROPER(TRIM(D29)) -> Wh-A | G29: 0 | H29: 197 | I29: 381.38 | J29: SUP46 | K29: =IF(OR(ISBLANK(G29), G29<=H29), "Low Stock - Reorder", "Healthy Stock") -> Low Stock - Reorder
A30: PRD29 | B30: Religious | C30: =PROPER(TRIM(B30)) -> Religious | D30: WH-C | E30: =PROPER(TRIM(D30)) -> Wh-C | F30: 753 | G30: 753 | H30: 93 | I30: 283.64 | J30: SUP71 | K30: =IF(OR(ISBLANK(G30), G30<=H30), "Low Stock - Reorder", "Healthy Stock") -> Healthy Stock
A31: PRD30 | B31: Well | C31: =PROPER(TRIM(B31)) -> Well | D31: WH-B | E31: =PROPER(TRIM(D31)) -> Wh-B | F31: 299 | G31: 299 | H31: 90 | I31: 7.86 | J31: SUP24 | K31: =IF(OR(ISBLANK(G31), G31<=H31), "Low Stock - Reorder", "Healthy Stock") -> Healthy Stock
A32: PRD31 | B32: Use | C32: =PROPER(TRIM(B32)) -> Use | D32: WH-A | E32: =PROPER(TRIM(D32)) -> Wh-A | F32: 365 | G32: 365 | H32: 62 | I32: 256.96 | J32: SUP88 | K32: =IF(OR(ISBLANK(G32), G32<=H32), "Low Stock - Reorder", "Healthy Stock") -> Healthy Stock
A33: PRD32 | B33: Use | C33: =PROPER(TRIM(B33)) -> Use | D33: WH-C | E33: =PROPER(TRIM(D33)) -> Wh-C | F33: 142 | G33: 142 | H33: 162 | I33: 437.11 | J33: SUP71 | K33: =IF(OR(ISBLANK(G33), G33<=H33), "Low Stock - Reorder", "Healthy Stock") -> Low Stock - Reorder
A34: PRD33 | B34: Free | C34: =PROPER(TRIM(B34)) -> Free | D34: WH-A | E34: =PROPER(TRIM(D34)) -> Wh-A | F34: 123 | G34: 123 | H34: 156 | I34: 305.6 | J34: SUP22 | K34: =IF(OR(ISBLANK(G34), G34<=H34), "Low Stock - Reorder", "Healthy Stock") -> Low Stock - Reorder
A35: PRD34 | B35: Old | C35: =PROPER(TRIM(B35)) -> Old | D35: WH-C | E35: =PROPER(TRIM(D35)) -> Wh-C | F35: 988 | G35: 988 | H35: 133 | I35: 380.83 | J35: SUP62 | K35: =IF(OR(ISBLANK(G35), G35<=H35), "Low Stock - Reorder", "Healthy Stock") -> Healthy Stock
A36: PRD35 | B36: Sea | C36: =PROPER(TRIM(B36)) -> Sea | D36: WH-B | E36: =PROPER(TRIM(D36)) -> Wh-B | F36: 729 | G36: 729 | H36: 121 | I36: 376.17 | J36: SUP77 | K36: =IF(OR(ISBLANK(G36), G36<=H36), "Low Stock - Reorder", "Healthy Stock") -> Healthy Stock
A37: PRD36 | B37: Color | C37: =PROPER(TRIM(B37)) -> Color | D37: WH-A | E37: =PROPER(TRIM(D37)) -> Wh-A | G37: 0 | H37: 111 | I37: 31.82 | J37: SUP89 | K37: =IF(OR(ISBLANK(G37), G37<=H37), "Low Stock - Reorder", "Healthy Stock") -> Low Stock - Reorder
A38: PRD37 | B38: So | C38: =PROPER(TRIM(B38)) -> So | D38: WH-B | E38: =PROPER(TRIM(D38)) -> Wh-B | F38: 374 | G38: 374 | H38: 93 | I38: 245.74 | J38: SUP77 | K38: =IF(OR(ISBLANK(G38), G38<=H38), "Low Stock - Reorder", "Healthy Stock") -> Healthy Stock
A39: PRD38 | B39: Surface | C39: =PROPER(TRIM(B39)) -> Surface | D39: wh-a | E39: =PROPER(TRIM(D39)) -> Wh-A | F39: 833 | G39: 833 | H39: 111 | I39: 282.77 | J39: SUP65 | K39: =IF(OR(ISBLANK(G39), G39<=H39), "Low Stock - Reorder", "Healthy Stock") -> Healthy Stock
A40: PRD39 | B40: Reveal | C40: =PROPER(TRIM(B40)) -> Reveal | D40: WH-C | E40: =PROPER(TRIM(D40)) -> Wh-C | F40: 302 | G40: 302 | H40: 109 | I40: 243.51 | J40: SUP51 | K40: =IF(OR(ISBLANK(G40), G40<=H40), "Low Stock - Reorder", "Healthy Stock") -> Healthy Stock
A41: PRD40 | B41: Important | C41: =PROPER(TRIM(B41)) -> Important | D41: WH-C | E41: =PROPER(TRIM(D41)) -> Wh-C | F41: 263 | G41: 263 | H41: 199 | I41: 297.98 | J41: SUP20 | K41: =IF(OR(ISBLANK(G41), G41<=H41), "Low Stock - Reorder", "Healthy Stock") -> Healthy Stock
A42: PRD41 | B42: Fear | C42: =PROPER(TRIM(B42)) -> Fear | D42: WH-C | E42: =PROPER(TRIM(D42)) -> Wh-C | F42: 755 | G42: 755 | H42: 98 | I42: 116.26 | J42: SUP4 | K42: =IF(OR(ISBLANK(G42), G42<=H42), "Low Stock - Reorder", "Healthy Stock") -> Healthy Stock
A43: PRD42 | B43: Organization | C43: =PROPER(TRIM(B43)) -> Organization | D43: wh-a | E43: =PROPER(TRIM(D43)) -> Wh-A | G43: 0 | H43: 74 | I43: 147.3 | J43: SUP53 | K43: =IF(OR(ISBLANK(G43), G43<=H43), "Low Stock - Reorder", "Healthy Stock") -> Low Stock - Reorder
A44: PRD43 | B44: Environmental | C44: =PROPER(TRIM(B44)) -> Environmental | D44: WH-B | E44: =PROPER(TRIM(D44)) -> Wh-B | F44: 849 | G44: 849 | H44: 61 | I44: 260.09 | J44: SUP3 | K44: =IF(OR(ISBLANK(G44), G44<=H44), "Low Stock - Reorder", "Healthy Stock") -> Healthy Stock
A45: PRD44 | B45: Guy | C45: =PROPER(TRIM(B45)) -> Guy | D45: WH-C | E45: =PROPER(TRIM(D45)) -> Wh-C | F45: 997 | G45: 997 | H45: 119 | I45: 468.99 | J45: SUP66 | K45: =IF(OR(ISBLANK(G45), G45<=H45), "Low Stock - Reorder", "Healthy Stock") -> Healthy Stock
A46: PRD45 | B46: Provide | C46: =PROPER(TRIM(B46)) -> Provide | D46: wh-a | E46: =PROPER(TRIM(D46)) -> Wh-A | F46: 676 | G46: 676 | H46: 135 | I46: 294.35 | J46: SUP41 | K46: =IF(OR(ISBLANK(G46), G46<=H46), "Low Stock - Reorder", "Healthy Stock") -> Healthy Stock
A47: PRD46 | B47: Give | C47: =PROPER(TRIM(B47)) -> Give | D47: WH-A | E47: =PROPER(TRIM(D47)) -> Wh-A | F47: 570 | G47: 570 | H47: 104 | I47: 235.98 | J47: SUP22 | K47: =IF(OR(ISBLANK(G47), G47<=H47), "Low Stock - Reorder", "Healthy Stock") -> Healthy Stock
A48: PRD47 | B48: From | C48: =PROPER(TRIM(B48)) -> From | D48: WH-A | E48: =PROPER(TRIM(D48)) -> Wh-A | F48: 60 | G48: 60 | H48: 173 | I48: 130.3 | J48: SUP33 | K48: =IF(OR(ISBLANK(G48), G48<=H48), "Low Stock - Reorder", "Healthy Stock") -> Low Stock - Reorder
A49: PRD48 | B49: Feeling | C49: =PROPER(TRIM(B49)) -> Feeling | D49: wh-a | E49: =PROPER(TRIM(D49)) -> Wh-A | F49: 586 | G49: 586 | H49: 195 | I49: 58.07 | J49: SUP10 | K49: =IF(OR(ISBLANK(G49), G49<=H49), "Low Stock - Reorder", "Healthy Stock") -> Healthy Stock
A50: PRD49 | B50: Experience | C50: =PROPER(TRIM(B50)) -> Experience | D50: wh-a | E50: =PROPER(TRIM(D50)) -> Wh-A | G50: 0 | H50: 114 | I50: 427.78 | J50: SUP2 | K50: =IF(OR(ISBLANK(G50), G50<=H50), "Low Stock - Reorder", "Healthy Stock") -> Low Stock - Reorder
A51: PRD50 | B51: Increase | C51: =PROPER(TRIM(B51)) -> Increase | D51: WH-A | E51: =PROPER(TRIM(D51)) -> Wh-A | G51: 0 | H51: 141 | I51: 200.27 | J51: SUP87 | K51: =IF(OR(ISBLANK(G51), G51<=H51), "Low Stock - Reorder", "Healthy Stock") -> Low Stock - Reorder
A52: PRD51 | B52: Recently | C52: =PROPER(TRIM(B52)) -> Recently | D52: WH-C | E52: =PROPER(TRIM(D52)) -> Wh-C | G52: 0 | H52: 134 | I52: 338.73 | J52: SUP63 | K52: =IF(OR(ISBLANK(G52), G52<=H52), "Low Stock - Reorder", "Healthy Stock") -> Low Stock - Reorder
A53: PRD52 | B53: Decide | C53: =PROPER(TRIM(B53)) -> Decide | D53: WH-B | E53: =PROPER(TRIM(D53)) -> Wh-B | G53: 0 | H53: 121 | I53: 301.44 | J53: SUP52 | K53: =IF(OR(ISBLANK(G53), G53<=H53), "Low Stock - Reorder", "Healthy Stock") -> Low Stock - Reorder
A54: PRD53 | B54: Provide | C54: =PROPER(TRIM(B54)) -> Provide | D54: wh-a | E54: =PROPER(TRIM(D54)) -> Wh-A | F54: 968 | G54: 968 | H54: 163 | I54: 71.87 | J54: SUP51 | K54: =IF(OR(ISBLANK(G54), G54<=H54), "Low Stock - Reorder", "Healthy Stock") -> Healthy Stock
A55: PRD54 | B55: Federal | C55: =PROPER(TRIM(B55)) -> Federal | D55: wh-a | E55: =PROPER(TRIM(D55)) -> Wh-A | F55: 747 | G55: 747 | H55: 124 | I55: 426.34 | J55: SUP61 | K55: =IF(OR(ISBLANK(G55), G55<=H55), "Low Stock - Reorder", "Healthy Stock") -> Healthy Stock
A56: PRD55 | B56: List | C56: =PROPER(TRIM(B56)) -> List | D56: WH-C | E56: =PROPER(TRIM(D56)) -> Wh-C | F56: 106 | G56: 106 | H56: 51 | I56: 281.37 | J56: SUP70 | K56: =IF(OR(ISBLANK(G56), G56<=H56), "Low Stock - Reorder", "Healthy Stock") -> Healthy Stock
A57: PRD56 | B57: House | C57: =PROPER(TRIM(B57)) -> House | D57: WH-A | E57: =PROPER(TRIM(D57)) -> Wh-A | G57: 0 | H57: 182 | I57: 299.13 | J57: SUP65 | K57: =IF(OR(ISBLANK(G57), G57<=H57), "Low Stock - Reorder", "Healthy Stock") -> Low Stock - Reorder
A58: PRD57 | B58: Old | C58: =PROPER(TRIM(B58)) -> Old | D58: WH-B | E58: =PROPER(TRIM(D58)) -> Wh-B | F58: 364 | G58: 364 | H58: 186 | I58: 340.8 | J58: SUP75 | K58: =IF(OR(ISBLANK(G58), G58<=H58), "Low Stock - Reorder", "Healthy Stock") -> Healthy Stock
A59: PRD58 | B59: Apply | C59: =PROPER(TRIM(B59)) -> Apply | D59: WH-C | E59: =PROPER(TRIM(D59)) -> Wh-C | G59: 0 | H59: 105 | I59: 292.53 | J59: SUP100 | K59: =IF(OR(ISBLANK(G59), G59<=H59), "Low Stock - Reorder", "Healthy Stock") -> Low Stock - Reorder
A60: PRD59 | B60: Low | C60: =PROPER(TRIM(B60)) -> Low | D60: WH-C | E60: =PROPER(TRIM(D60)) -> Wh-C | G60: 0 | H60: 54 | I60: 72.68 | J60: SUP78 | K60: =IF(OR(ISBLANK(G60), G60<=H60), "Low Stock - Reorder", "Healthy Stock") -> Low Stock - Reorder
A61: PRD60 | B61: Close | C61: =PROPER(TRIM(B61)) -> Close | D61: WH-C | E61: =PROPER(TRIM(D61)) -> Wh-C | G61: 0 | H61: 145 | I61: 70.54 | J61: SUP56 | K61: =IF(OR(ISBLANK(G61), G61<=H61), "Low Stock - Reorder", "Healthy Stock") -> Low Stock - Reorder
A62: PRD61 | B62: Phone | C62: =PROPER(TRIM(B62)) -> Phone | D62: wh-a | E62: =PROPER(TRIM(D62)) -> Wh-A | G62: 0 | H62: 193 | I62: 467.98 | J62: SUP28 | K62: =IF(OR(ISBLANK(G62), G62<=H62), "Low Stock - Reorder", "Healthy Stock") -> Low Stock - Reorder
A63: PRD62 | B63: Long | C63: =PROPER(TRIM(B63)) -> Long | D63: WH-A | E63: =PROPER(TRIM(D63)) -> Wh-A | F63: 437 | G63: 437 | H63: 152 | I63: 237.59 | J63: SUP9 | K63: =IF(OR(ISBLANK(G63), G63<=H63), "Low Stock - Reorder", "Healthy Stock") -> Healthy Stock
A64: PRD63 | B64: Wide | C64: =PROPER(TRIM(B64)) -> Wide | D64: wh-a | E64: =PROPER(TRIM(D64)) -> Wh-A | F64: 322 | G64: 322 | H64: 116 | I64: 417.94 | J64: SUP71 | K64: =IF(OR(ISBLANK(G64), G64<=H64), "Low Stock - Reorder", "Healthy Stock") -> Healthy Stock
A65: PRD64 | B65: Loss | C65: =PROPER(TRIM(B65)) -> Loss | D65: WH-A | E65: =PROPER(TRIM(D65)) -> Wh-A | G65: 0 | H65: 112 | I65: 246.3 | J65: SUP35 | K65: =IF(OR(ISBLANK(G65), G65<=H65), "Low Stock - Reorder", "Healthy Stock") -> Low Stock - Reorder
A66: PRD65 | B66: Ground | C66: =PROPER(TRIM(B66)) -> Ground | D66: WH-B | E66: =PROPER(TRIM(D66)) -> Wh-B | F66: 624 | G66: 624 | H66: 106 | I66: 10.65 | J66: SUP80 | K66: =IF(OR(ISBLANK(G66), G66<=H66), "Low Stock - Reorder", "Healthy Stock") -> Healthy Stock
A67: PRD66 | B67: Enter | C67: =PROPER(TRIM(B67)) -> Enter | D67: WH-C | E67: =PROPER(TRIM(D67)) -> Wh-C | G67: 0 | H67: 84 | I67: 371.55 | J67: SUP51 | K67: =IF(OR(ISBLANK(G67), G67<=H67), "Low Stock - Reorder", "Healthy Stock") -> Low Stock - Reorder
A68: PRD67 | B68: New | C68: =PROPER(TRIM(B68)) -> New | D68: WH-A | E68: =PROPER(TRIM(D68)) -> Wh-A | G68: 0 | H68: 98 | I68: 94.52 | J68: SUP72 | K68: =IF(OR(ISBLANK(G68), G68<=H68), "Low Stock - Reorder", "Healthy Stock") -> Low Stock - Reorder
A69: PRD68 | B69: Second | C69: =PROPER(TRIM(B69)) -> Second | D69: wh-a | E69: =PROPER(TRIM(D69)) -> Wh-A | F69: 900 | G69: 900 | H69: 124 | I69: 353.88 | J69: SUP4 | K69: =IF(OR(ISBLANK(G69), G69<=H69), "Low Stock - Reorder", "Healthy Stock") -> Healthy Stock
A70: PRD69 | B70: Feeling | C70: =PROPER(TRIM(B70)) -> Feeling | D70: WH-A | E70: =PROPER(TRIM(D70)) -> Wh-A | G70: 0 | H70: 175 | I70: 418.7 | J70: SUP39 | K70: =IF(OR(ISBLANK(G70), G70<=H70), "Low Stock - Reorder", "Healthy Stock") -> Low Stock - Reorder
A71: PRD70 | B71: Cause | C71: =PROPER(TRIM(B71)) -> Cause | D71: wh-a | E71: =PROPER(TRIM(D71)) -> Wh-A | G71: 0 | H71: 175 | I71: 104.84 | J71: SUP84 | K71: =IF(OR(ISBLANK(G71), G71<=H71), "Low Stock - Reorder", "Healthy Stock") -> Low Stock - Reorder
A72: PRD71 | B72: All | C72: =PROPER(TRIM(B72)) -> All | D72: wh-a | E72: =PROPER(TRIM(D72)) -> Wh-A | G72: 0 | H72: 59 | I72: 141.35 | J72: SUP76 | K72: =IF(OR(ISBLANK(G72), G72<=H72), "Low Stock - Reorder", "Healthy Stock") -> Low Stock - Reorder
A73: PRD72 | B73: Air | C73: =PROPER(TRIM(B73)) -> Air | D73: WH-A | E73: =PROPER(TRIM(D73)) -> Wh-A | G73: 0 | H73: 167 | I73: 269.33 | J73: SUP78 | K73: =IF(OR(ISBLANK(G73), G73<=H73), "Low Stock - Reorder", "Healthy Stock") -> Low Stock - Reorder
A74: PRD73 | B74: Among | C74: =PROPER(TRIM(B74)) -> Among | D74: WH-C | E74: =PROPER(TRIM(D74)) -> Wh-C | G74: 0 | H74: 136 | I74: 289.61 | J74: SUP58 | K74: =IF(OR(ISBLANK(G74), G74<=H74), "Low Stock - Reorder", "Healthy Stock") -> Low Stock - Reorder
A75: PRD74 | B75: Girl | C75: =PROPER(TRIM(B75)) -> Girl | D75: WH-B | E75: =PROPER(TRIM(D75)) -> Wh-B | G75: 0 | H75: 74 | I75: 391 | J75: SUP5 | K75: =IF(OR(ISBLANK(G75), G75<=H75), "Low Stock - Reorder", "Healthy Stock") -> Low Stock - Reorder
A76: PRD75 | B76: Interview | C76: =PROPER(TRIM(B76)) -> Interview | D76: WH-B | E76: =PROPER(TRIM(D76)) -> Wh-B | G76: 0 | H76: 55 | I76: 174.85 | J76: SUP27 | K76: =IF(OR(ISBLANK(G76), G76<=H76), "Low Stock - Reorder", "Healthy Stock") -> Low Stock - Reorder
A77: PRD76 | B77: Position | C77: =PROPER(TRIM(B77)) -> Position | D77: wh-a | E77: =PROPER(TRIM(D77)) -> Wh-A | F77: 554 | G77: 554 | H77: 63 | I77: 261.85 | J77: SUP96 | K77: =IF(OR(ISBLANK(G77), G77<=H77), "Low Stock - Reorder", "Healthy Stock") -> Healthy Stock
A78: PRD77 | B78: Follow | C78: =PROPER(TRIM(B78)) -> Follow | D78: WH-A | E78: =PROPER(TRIM(D78)) -> Wh-A | F78: 300 | G78: 300 | H78: 177 | I78: 483.36 | J78: SUP41 | K78: =IF(OR(ISBLANK(G78), G78<=H78), "Low Stock - Reorder", "Healthy Stock") -> Healthy Stock
A79: PRD78 | B79: From | C79: =PROPER(TRIM(B79)) -> From | D79: wh-a | E79: =PROPER(TRIM(D79)) -> Wh-A | G79: 0 | H79: 104 | I79: 20.69 | J79: SUP92 | K79: =IF(OR(ISBLANK(G79), G79<=H79), "Low Stock - Reorder", "Healthy Stock") -> Low Stock - Reorder
A80: PRD79 | B80: Worry | C80: =PROPER(TRIM(B80)) -> Worry | D80: WH-B | E80: =PROPER(TRIM(D80)) -> Wh-B | F80: 824 | G80: 824 | H80: 178 | I80: 331.82 | J80: SUP65 | K80: =IF(OR(ISBLANK(G80), G80<=H80), "Low Stock - Reorder", "Healthy Stock") -> Healthy Stock
A81: PRD80 | B81: End | C81: =PROPER(TRIM(B81)) -> End | D81: wh-a | E81: =PROPER(TRIM(D81)) -> Wh-A | G81: 0 | H81: 67 | I81: 340.33 | J81: SUP55 | K81: =IF(OR(ISBLANK(G81), G81<=H81), "Low Stock - Reorder", "Healthy Stock") -> Low Stock - Reorder
A82: PRD81 | B82: Quickly | C82: =PROPER(TRIM(B82)) -> Quickly | D82: WH-A | E82: =PROPER(TRIM(D82)) -> Wh-A | G82: 0 | H82: 179 | I82: 233.98 | J82: SUP30 | K82: =IF(OR(ISBLANK(G82), G82<=H82), "Low Stock - Reorder", "Healthy Stock") -> Low Stock - Reorder
A83: PRD82 | B83: Career | C83: =PROPER(TRIM(B83)) -> Career | D83: wh-a | E83: =PROPER(TRIM(D83)) -> Wh-A | G83: 0 | H83: 67 | I83: 63.76 | J83: SUP34 | K83: =IF(OR(ISBLANK(G83), G83<=H83), "Low Stock - Reorder", "Healthy Stock") -> Low Stock - Reorder
A84: PRD83 | B84: Begin | C84: =PROPER(TRIM(B84)) -> Begin | D84: WH-C | E84: =PROPER(TRIM(D84)) -> Wh-C | G84: 0 | H84: 165 | I84: 466.86 | J84: SUP15 | K84: =IF(OR(ISBLANK(G84), G84<=H84), "Low Stock - Reorder", "Healthy Stock") -> Low Stock - Reorder
A85: PRD84 | B85: Eye | C85: =PROPER(TRIM(B85)) -> Eye | D85: WH-B | E85: =PROPER(TRIM(D85)) -> Wh-B | G85: 0 | H85: 172 | I85: 348.65 | J85: SUP71 | K85: =IF(OR(ISBLANK(G85), G85<=H85), "Low Stock - Reorder", "Healthy Stock") -> Low Stock - Reorder
A86: PRD85 | B86: Change | C86: =PROPER(TRIM(B86)) -> Change | D86: WH-A | E86: =PROPER(TRIM(D86)) -> Wh-A | F86: 566 | G86: 566 | H86: 200 | I86: 420.83 | J86: SUP22 | K86: =IF(OR(ISBLANK(G86), G86<=H86), "Low Stock - Reorder", "Healthy Stock") -> Healthy Stock
A87: PRD86 | B87: Individual | C87: =PROPER(TRIM(B87)) -> Individual | D87: wh-a | E87: =PROPER(TRIM(D87)) -> Wh-A | G87: 0 | H87: 92 | I87: 132.84 | J87: SUP87 | K87: =IF(OR(ISBLANK(G87), G87<=H87), "Low Stock - Reorder", "Healthy Stock") -> Low Stock - Reorder
A88: PRD87 | B88: And | C88: =PROPER(TRIM(B88)) -> And | D88: WH-A | E88: =PROPER(TRIM(D88)) -> Wh-A | G88: 0 | H88: 56 | I88: 320.9 | J88: SUP38 | K88: =IF(OR(ISBLANK(G88), G88<=H88), "Low Stock - Reorder", "Healthy Stock") -> Low Stock - Reorder
A89: PRD88 | B89: Across | C89: =PROPER(TRIM(B89)) -> Across | D89: WH-A | E89: =PROPER(TRIM(D89)) -> Wh-A | G89: 0 | H89: 193 | I89: 390.3 | J89: SUP48 | K89: =IF(OR(ISBLANK(G89), G89<=H89), "Low Stock - Reorder", "Healthy Stock") -> Low Stock - Reorder
A90: PRD89 | B90: Reality | C90: =PROPER(TRIM(B90)) -> Reality | D90: WH-B | E90: =PROPER(TRIM(D90)) -> Wh-B | F90: 476 | G90: 476 | H90: 65 | I90: 354.55 | J90: SUP36 | K90: =IF(OR(ISBLANK(G90), G90<=H90), "Low Stock - Reorder", "Healthy Stock") -> Healthy Stock
A91: PRD90 | B91: Story | C91: =PROPER(TRIM(B91)) -> Story | D91: WH-B | E91: =PROPER(TRIM(D91)) -> Wh-B | G91: 0 | H91: 102 | I91: 66.37 | J91: SUP42 | K91: =IF(OR(ISBLANK(G91), G91<=H91), "Low Stock - Reorder", "Healthy Stock") -> Low Stock - Reorder
A92: PRD91 | B92: Mouth | C92: =PROPER(TRIM(B92)) -> Mouth | D92: WH-C | E92: =PROPER(TRIM(D92)) -> Wh-C | G92: 0 | H92: 176 | I92: 15.79 | J92: SUP16 | K92: =IF(OR(ISBLANK(G92), G92<=H92), "Low Stock - Reorder", "Healthy Stock") -> Low Stock - Reorder
A93: PRD92 | B93: Throw | C93: =PROPER(TRIM(B93)) -> Throw | D93: wh-a | E93: =PROPER(TRIM(D93)) -> Wh-A | G93: 0 | H93: 115 | I93: 275.98 | J93: SUP13 | K93: =IF(OR(ISBLANK(G93), G93<=H93), "Low Stock - Reorder", "Healthy Stock") -> Low Stock - Reorder
A94: PRD93 | B94: Mrs | C94: =PROPER(TRIM(B94)) -> Mrs | D94: WH-C | E94: =PROPER(TRIM(D94)) -> Wh-C | G94: 0 | H94: 50 | I94: 7.37 | J94: SUP96 | K94: =IF(OR(ISBLANK(G94), G94<=H94), "Low Stock - Reorder", "Healthy Stock") -> Low Stock - Reorder
A95: PRD94 | B95: Natural | C95: =PROPER(TRIM(B95)) -> Natural | D95: WH-C | E95: =PROPER(TRIM(D95)) -> Wh-C | G95: 0 | H95: 144 | I95: 208.1 | J95: SUP20 | K95: =IF(OR(ISBLANK(G95), G95<=H95), "Low Stock - Reorder", "Healthy Stock") -> Low Stock - Reorder
A96: PRD95 | B96: Spring | C96: =PROPER(TRIM(B96)) -> Spring | D96: WH-B | E96: =PROPER(TRIM(D96)) -> Wh-B | F96: 792 | G96: 792 | H96: 63 | I96: 364.66 | J96: SUP40 | K96: =IF(OR(ISBLANK(G96), G96<=H96), "Low Stock - Reorder", "Healthy Stock") -> Healthy Stock
A97: PRD96 | B97: Election | C97: =PROPER(TRIM(B97)) -> Election | D97: WH-A | E97: =PROPER(TRIM(D97)) -> Wh-A | G97: 0 | H97: 90 | I97: 294.23 | J97: SUP68 | K97: =IF(OR(ISBLANK(G97), G97<=H97), "Low Stock - Reorder", "Healthy Stock") -> Low Stock - Reorder
A98: PRD97 | B98: Myself | C98: =PROPER(TRIM(B98)) -> Myself | D98: WH-B | E98: =PROPER(TRIM(D98)) -> Wh-B | G98: 0 | H98: 128 | I98: 81.17 | J98: SUP27 | K98: =IF(OR(ISBLANK(G98), G98<=H98), "Low Stock - Reorder", "Healthy Stock") -> Low Stock - Reorder
A99: PRD98 | B99: Movement | C99: =PROPER(TRIM(B99)) -> Movement | D99: WH-C | E99: =PROPER(TRIM(D99)) -> Wh-C | G99: 0 | H99: 197 | I99: 412.3 | J99: SUP77 | K99: =IF(OR(ISBLANK(G99), G99<=H99), "Low Stock - Reorder", "Healthy Stock") -> Low Stock - Reorder
A100: PRD99 | B100: Feel | C100: =PROPER(TRIM(B100)) -> Feel | D100: WH-B | E100: =PROPER(TRIM(D100)) -> Wh-B | G100: 0 | H100: 79 | I100: 399.5 | J100: SUP83 | K100: =IF(OR(ISBLANK(G100), G100<=H100), "Low Stock - Reorder", "Healthy Stock") -> Low Stock - Reorder
...

Sheet Employees
A1: Emp_ID | B1: Employee_Name | C1: Clean_Name | D1: Department | E1: Clean_Department | F1: Salary | G1: Clean_Salary | H1: Joining_Date | I1: Clean_Date | J1: Performance_Score | K1: Performance_Category | L1: Average Salary | M1: =AVERAGE(G2:G401) -> 90115.762
A2: EMP1 | B2: Lauren West | C2: =PROPER(TRIM(B2)) -> Lauren West | D2: Finance | E2: =IF(UPPER(TRIM(D2))="IT", "IT", IF(UPPER(TRIM(D2))="HR", "HR", PROPER(TRIM(D2)))) -> Finance | F2: 46457 | G2: 46457 | H2: 10-06-2025 | I2: 45818 | J2: 4.3 | K2: =IF(J2>=4, "Excellent", IF(AND(J2>=2.5, J2<4), "Satisfactory", "Needs Improvement")) -> Excellent | L2: Average Sales Department Salary | M2: =AVERAGEIF(Employees!E:E, "Sales", Employees!G:G) -> 90746.986
A3: EMP2 | B3: Brandon Bauer | C3: =PROPER(TRIM(B3)) -> Brandon Bauer | D3: Sales | E3: =IF(UPPER(TRIM(D3))="IT", "IT", IF(UPPER(TRIM(D3))="HR", "HR", PROPER(TRIM(D3)))) -> Sales | F3: 47537 | G3: 47537 | H3: 22-05-2025 | I3: 45799 | J3: 3.8 | K3: =IF(J3>=4, "Excellent", IF(AND(J3>=2.5, J3<4), "Satisfactory", "Needs Improvement")) -> Satisfactory
A4: EMP3 | B4: Blake Keller | C4: =PROPER(TRIM(B4)) -> Blake Keller | D4: Sales | E4: =IF(UPPER(TRIM(D4))="IT", "IT", IF(UPPER(TRIM(D4))="HR", "HR", PROPER(TRIM(D4)))) -> Sales | F4: 56939 | G4: 56939 | H4: 12-04-2024 | I4: 45394 | J4: 2.9 | K4: =IF(J4>=4, "Excellent", IF(AND(J4>=2.5, J4<4), "Satisfactory", "Needs Improvement")) -> Satisfactory | L4: Vlookup | M4: Name | N4: Department
A5: EMP4 | B5: Michelle Bates MD | C5: =PROPER(TRIM(B5)) -> Michelle Bates Md | D5: sales | E5: =IF(UPPER(TRIM(D5))="IT", "IT", IF(UPPER(TRIM(D5))="HR", "HR", PROPER(TRIM(D5)))) -> Sales | F5: 148328 | G5: 148328 | H5: 04-02-2024 | I5: 45326 | J5: 1.5 | K5: =IF(J5>=4, "Excellent", IF(AND(J5>=2.5, J5<4), "Satisfactory", "Needs Improvement")) -> Needs Improvement | M5: =VLOOKUP(A5, Employees!A:D, 3, FALSE) -> Michelle Bates Md | N5: =VLOOKUP(A5, Employees!A:D, 4, FALSE) -> sales
A6: EMP5 | B6: Joshua Taylor | C6: =PROPER(TRIM(B6)) -> Joshua Taylor | D6: sales | E6: =IF(UPPER(TRIM(D6))="IT", "IT", IF(UPPER(TRIM(D6))="HR", "HR", PROPER(TRIM(D6)))) -> Sales | F6: 39734 | G6: 39734 | H6: 15-02-2024 | I6: 45337 | J6: 4.8 | K6: =IF(J6>=4, "Excellent", IF(AND(J6>=2.5, J6<4), "Satisfactory", "Needs Improvement")) -> Excellent
A7: EMP6 | B7: Bryan Huffman | C7: =PROPER(TRIM(B7)) -> Bryan Huffman | D7: HR | E7: =IF(UPPER(TRIM(D7))="IT", "IT", IF(UPPER(TRIM(D7))="HR", "HR", PROPER(TRIM(D7)))) -> HR | F7: 132390 | G7: 132390 | H7: 08-10-2025 | I7: 45938 | J7: 4.4 | K7: =IF(J7>=4, "Excellent", IF(AND(J7>=2.5, J7<4), "Satisfactory", "Needs Improvement")) -> Excellent
A8: EMP7 | B8: Angela Booker | C8: =PROPER(TRIM(B8)) -> Angela Booker | D8: IT | E8: =IF(UPPER(TRIM(D8))="IT", "IT", IF(UPPER(TRIM(D8))="HR", "HR", PROPER(TRIM(D8)))) -> IT | F8: 60463 | G8: 60463 | H8: 30-04-2026 | I8: 46142 | J8: 2.2 | K8: =IF(J8>=4, "Excellent", IF(AND(J8>=2.5, J8<4), "Satisfactory", "Needs Improvement")) -> Needs Improvement
A9: EMP8 | B9: Norma Floyd | C9: =PROPER(TRIM(B9)) -> Norma Floyd | D9: Sales | E9: =IF(UPPER(TRIM(D9))="IT", "IT", IF(UPPER(TRIM(D9))="HR", "HR", PROPER(TRIM(D9)))) -> Sales | F9: 57214 | G9: 57214 | H9: 13-10-2024 | I9: 45578 | J9: 3.7 | K9: =IF(J9>=4, "Excellent", IF(AND(J9>=2.5, J9<4), "Satisfactory", "Needs Improvement")) -> Satisfactory
A10: EMP9 | B10: Andrew Thompson | C10: =PROPER(TRIM(B10)) -> Andrew Thompson | D10: HR | E10: =IF(UPPER(TRIM(D10))="IT", "IT", IF(UPPER(TRIM(D10))="HR", "HR", PROPER(TRIM(D10)))) -> HR | F10: 53784 | G10: 53784 | H10: 27-10-2025 | I10: 45957 | J10: 5 | K10: =IF(J10>=4, "Excellent", IF(AND(J10>=2.5, J10<4), "Satisfactory", "Needs Improvement")) -> Excellent
A11: EMP10 | B11: Anthony Romero | C11: =PROPER(TRIM(B11)) -> Anthony Romero | D11: sales | E11: =IF(UPPER(TRIM(D11))="IT", "IT", IF(UPPER(TRIM(D11))="HR", "HR", PROPER(TRIM(D11)))) -> Sales | F11: 79199 | G11: 79199 | H11: 01-08-2024 | I11: 45505 | J11: 2 | K11: =IF(J11>=4, "Excellent", IF(AND(J11>=2.5, J11<4), "Satisfactory", "Needs Improvement")) -> Needs Improvement
A12: EMP11 | B12: Michael Meyers | C12: =PROPER(TRIM(B12)) -> Michael Meyers | D12: Operations | E12: =IF(UPPER(TRIM(D12))="IT", "IT", IF(UPPER(TRIM(D12))="HR", "HR", PROPER(TRIM(D12)))) -> Operations | F12: 82177 | G12: 82177 | H12: 11-10-2024 | I12: 45576 | J12: 1.3 | K12: =IF(J12>=4, "Excellent", IF(AND(J12>=2.5, J12<4), "Satisfactory", "Needs Improvement")) -> Needs Improvement
A13: EMP12 | B13: Billy Turner | C13: =PROPER(TRIM(B13)) -> Billy Turner | D13: IT | E13: =IF(UPPER(TRIM(D13))="IT", "IT", IF(UPPER(TRIM(D13))="HR", "HR", PROPER(TRIM(D13)))) -> IT | F13: 113665 | G13: 113665 | H13: 02-07-2024 | I13: 45475 | J13: 3.4 | K13: =IF(J13>=4, "Excellent", IF(AND(J13>=2.5, J13<4), "Satisfactory", "Needs Improvement")) -> Satisfactory
A14: EMP13 | B14: Tammy Price | C14: =PROPER(TRIM(B14)) -> Tammy Price | D14: Finance | E14: =IF(UPPER(TRIM(D14))="IT", "IT", IF(UPPER(TRIM(D14))="HR", "HR", PROPER(TRIM(D14)))) -> Finance | F14: 117027 | G14: 117027 | H14: 22-05-2025 | I14: 45799 | J14: 1.2 | K14: =IF(J14>=4, "Excellent", IF(AND(J14>=2.5, J14<4), "Satisfactory", "Needs Improvement")) -> Needs Improvement
A15: EMP14 | B15: David Riley | C15: =PROPER(TRIM(B15)) -> David Riley | D15: Sales | E15: =IF(UPPER(TRIM(D15))="IT", "IT", IF(UPPER(TRIM(D15))="HR", "HR", PROPER(TRIM(D15)))) -> Sales | F15: 73355 | G15: 73355 | H15: 03-06-2024 | I15: 45446 | J15: 1.4 | K15: =IF(J15>=4, "Excellent", IF(AND(J15>=2.5, J15<4), "Satisfactory", "Needs Improvement")) -> Needs Improvement
A16: EMP15 | B16: Frank Lewis | C16: =PROPER(TRIM(B16)) -> Frank Lewis | D16: sales | E16: =IF(UPPER(TRIM(D16))="IT", "IT", IF(UPPER(TRIM(D16))="HR", "HR", PROPER(TRIM(D16)))) -> Sales | F16: 124641 | G16: 124641 | H16: 31-03-2024 | I16: 45382 | J16: 2.1 | K16: =IF(J16>=4, "Excellent", IF(AND(J16>=2.5, J16<4), "Satisfactory", "Needs Improvement")) -> Needs Improvement
A17: EMP16 | B17: Jordan Wallace | C17: =PROPER(TRIM(B17)) -> Jordan Wallace | D17: sales | E17: =IF(UPPER(TRIM(D17))="IT", "IT", IF(UPPER(TRIM(D17))="HR", "HR", PROPER(TRIM(D17)))) -> Sales | G17: 0 | H17: 21-08-2024 | I17: 45525 | J17: 4.8 | K17: =IF(J17>=4, "Excellent", IF(AND(J17>=2.5, J17<4), "Satisfactory", "Needs Improvement")) -> Excellent
A18: EMP17 | B18: Susan Rollins | C18: =PROPER(TRIM(B18)) -> Susan Rollins | D18: HR | E18: =IF(UPPER(TRIM(D18))="IT", "IT", IF(UPPER(TRIM(D18))="HR", "HR", PROPER(TRIM(D18)))) -> HR | F18: 92239 | G18: 92239 | H18: 13-05-2024 | I18: 45425 | J18: 3.6 | K18: =IF(J18>=4, "Excellent", IF(AND(J18>=2.5, J18<4), "Satisfactory", "Needs Improvement")) -> Satisfactory
A19: EMP18 | B19: Thomas Green | C19: =PROPER(TRIM(B19)) -> Thomas Green | D19: sales | E19: =IF(UPPER(TRIM(D19))="IT", "IT", IF(UPPER(TRIM(D19))="HR", "HR", PROPER(TRIM(D19)))) -> Sales | F19: 79981 | G19: 79981 | H19: 03-06-2025 | I19: 45811 | J19: 2.5 | K19: =IF(J19>=4, "Excellent", IF(AND(J19>=2.5, J19<4), "Satisfactory", "Needs Improvement")) -> Satisfactory
A20: EMP19 | B20: Maria Walker | C20: =PROPER(TRIM(B20)) -> Maria Walker | D20: Operations | E20: =IF(UPPER(TRIM(D20))="IT", "IT", IF(UPPER(TRIM(D20))="HR", "HR", PROPER(TRIM(D20)))) -> Operations | F20: 125711 | G20: 125711 | H20: 01-02-2026 | I20: 46054 | J20: 4.2 | K20: =IF(J20>=4, "Excellent", IF(AND(J20>=2.5, J20<4), "Satisfactory", "Needs Improvement")) -> Excellent
A21: EMP20 | B21: Lisa Patton | C21: =PROPER(TRIM(B21)) -> Lisa Patton | D21: Operations | E21: =IF(UPPER(TRIM(D21))="IT", "IT", IF(UPPER(TRIM(D21))="HR", "HR", PROPER(TRIM(D21)))) -> Operations | F21: 100252 | G21: 100252 | H21: 07-01-2025 | I21: 45664 | J21: 1.7 | K21: =IF(J21>=4, "Excellent", IF(AND(J21>=2.5, J21<4), "Satisfactory", "Needs Improvement")) -> Needs Improvement
A22: EMP21 | B22: Dustin Greer | C22: =PROPER(TRIM(B22)) -> Dustin Greer | D22: HR | E22: =IF(UPPER(TRIM(D22))="IT", "IT", IF(UPPER(TRIM(D22))="HR", "HR", PROPER(TRIM(D22)))) -> HR | F22: 113034 | G22: 113034 | H22: 08-02-2026 | I22: 46061 | J22: 1.6 | K22: =IF(J22>=4, "Excellent", IF(AND(J22>=2.5, J22<4), "Satisfactory", "Needs Improvement")) -> Needs Improvement
A23: EMP22 | B23: Joseph Jackson | C23: =PROPER(TRIM(B23)) -> Joseph Jackson | D23: sales | E23: =IF(UPPER(TRIM(D23))="IT", "IT", IF(UPPER(TRIM(D23))="HR", "HR", PROPER(TRIM(D23)))) -> Sales | F23: 62219 | G23: 62219 | H23: 07-12-2024 | I23: 45633 | J23: 2.1 | K23: =IF(J23>=4, "Excellent", IF(AND(J23>=2.5, J23<4), "Satisfactory", "Needs Improvement")) -> Needs Improvement
A24: EMP23 | B24: Elizabeth Rangel | C24: =PROPER(TRIM(B24)) -> Elizabeth Rangel | D24: IT | E24: =IF(UPPER(TRIM(D24))="IT", "IT", IF(UPPER(TRIM(D24))="HR", "HR", PROPER(TRIM(D24)))) -> IT | F24: 50154 | G24: 50154 | H24: 21-06-2024 | I24: 45464 | J24: 2 | K24: =IF(J24>=4, "Excellent", IF(AND(J24>=2.5, J24<4), "Satisfactory", "Needs Improvement")) -> Needs Improvement
A25: EMP24 | B25: Brandon Wolfe | C25: =PROPER(TRIM(B25)) -> Brandon Wolfe | D25: Operations | E25: =IF(UPPER(TRIM(D25))="IT", "IT", IF(UPPER(TRIM(D25))="HR", "HR", PROPER(TRIM(D25)))) -> Operations | F25: 124932 | G25: 124932 | H25: 03-01-2025 | I25: 45660 | J25: 4.2 | K25: =IF(J25>=4, "Excellent", IF(AND(J25>=2.5, J25<4), "Satisfactory", "Needs Improvement")) -> Excellent
A26: EMP25 | B26: Hannah Ruiz | C26: =PROPER(TRIM(B26)) -> Hannah Ruiz | D26: Sales | E26: =IF(UPPER(TRIM(D26))="IT", "IT", IF(UPPER(TRIM(D26))="HR", "HR", PROPER(TRIM(D26)))) -> Sales | F26: 35958 | G26: 35958 | H26: 21-02-2026 | I26: 46074 | J26: 2.6 | K26: =IF(J26>=4, "Excellent", IF(AND(J26>=2.5, J26<4), "Satisfactory", "Needs Improvement")) -> Satisfactory
A27: EMP26 | B27: Joshua Scott | C27: =PROPER(TRIM(B27)) -> Joshua Scott | D27: HR | E27: =IF(UPPER(TRIM(D27))="IT", "IT", IF(UPPER(TRIM(D27))="HR", "HR", PROPER(TRIM(D27)))) -> HR | F27: 45194 | G27: 45194 | H27: 19-08-2024 | I27: 45523 | J27: 3.5 | K27: =IF(J27>=4, "Excellent", IF(AND(J27>=2.5, J27<4), "Satisfactory", "Needs Improvement")) -> Satisfactory
A28: EMP27 | B28: Christopher Sanchez | C28: =PROPER(TRIM(B28)) -> Christopher Sanchez | D28: HR | E28: =IF(UPPER(TRIM(D28))="IT", "IT", IF(UPPER(TRIM(D28))="HR", "HR", PROPER(TRIM(D28)))) -> HR | F28: 64909 | G28: 64909 | H28: 09-01-2025 | I28: 45666 | J28: 3.6 | K28: =IF(J28>=4, "Excellent", IF(AND(J28>=2.5, J28<4), "Satisfactory", "Needs Improvement")) -> Satisfactory
A29: EMP28 | B29: Patrick Lyons | C29: =PROPER(TRIM(B29)) -> Patrick Lyons | D29: Finance | E29: =IF(UPPER(TRIM(D29))="IT", "IT", IF(UPPER(TRIM(D29))="HR", "HR", PROPER(TRIM(D29)))) -> Finance | F29: 47721 | G29: 47721 | H29: 29-04-2025 | I29: 45776 | J29: 2.5 | K29: =IF(J29>=4, "Excellent", IF(AND(J29>=2.5, J29<4), "Satisfactory", "Needs Improvement")) -> Satisfactory
... A401: EMP400 | B401: Danielle Anderson | C401: =PROPER(TRIM(B401)) -> Danielle Anderson | D401: IT | E401: =IF(UPPER(TRIM(D401))="IT", "IT", IF(UPPER(TRIM(D401))="HR", "HR", PROPER(TRIM(D401)))) -> IT | F401: 74804 | G401: 74804 | H401: 04-07-2024 | I401: 45477 | J401: 3.3 | K401: =IF(J401>=4, "Excellent", IF(AND(J401>=2.5, J401<4), "Satisfactory", "Needs Improvement")) -> Satisfactory

Sheet Suppliers
A1: Supplier_ID | B1: Supplier_Name | C1: Country | D1: Lead_Time_Days | E1: Rating
A2: SUP1 | B2: Casey-Townsend | C2: Pakistan | D2: 33 | E2: 2.4
A3: SUP2 | B3: Anderson, Mahoney and Lane | C3: China | D3: 32 | E3: 2.5
A4: SUP3 | B4: Norris LLC | C4: Germany | D4: 24 | E4: 3.7
A5: SUP4 | B5: Jones-Fitzgerald | C5: Germany | D5: 3 | E5: 1.9
A6: SUP5 | B6: Sanchez Ltd | C6: Germany | D6: 40 | E6: 3.5
A7: SUP6 | B7: Patrick and Sons | C7: UAE | D7: 39 | E7: 2
A8: SUP7 | B8: Murphy-Carter | C8: Pakistan | D8: 26 | E8: 3.5
A9: SUP8 | B9: Hoffman-Cooper | C9: Germany | D9: 18 | E9: 2.6
A10: SUP9 | B10: Armstrong, Paul and Thompson | C10: Germany | D10: 13 | E10: 1.7
A11: SUP10 | B11: Ferguson, Mcpherson and Wheeler | C11: USA | D11: 40 | E11: 2
A12: SUP11 | B12: Collins, Reynolds and Chen | C12: USA | D12: 24 | E12: 2
A13: SUP12 | B13: Walton-Williams | C13: Germany | D13: 34 | E13: 4.5
... A101: SUP100 | B101: Espinoza-Sims | C101: UAE | D101: 11 | E101: 4

Sheet Logistics
A1: Shipment_ID | B1: Carrier | C1: Shipment_Date | D1: Clean_Date | E1: Transport_Cost | F1: Delivery_Status | I1: Highest Transport Cost | J1: =MAX(E2:E2001) -> 9992.22
A2: SHP1 | B2: DHL | C2: 2025/09/20 | D2: 45920 | E2: 8312.13 | F2: Delayed | I2: Lowest Transport Cost | J2: =MIN(E2:E2001) -> 100.77
A3: SHP2 | B3: TCS | C3: 2024/09/25 | D3: 45560 | E3: 9574.38 | F3: Lost | I3: Total Delayed Shipments | J3: =COUNTIF(Logistics!F:F, "Delayed") -> 694
A4: SHP3 | B4: UPS | C4: 2024/02/21 | D4: 45343 | E4: 4365.58 | F4: Lost
A5: SHP4 | B5: TCS | C5: 2025/07/08 | D5: 45846 | E5: 9006.67 | F5: On Time
A6: SHP5 | B6: FedEx | C6: 2025/05/29 | D6: 45806 | E6: 4853.3 | F6: On Time
A7: SHP6 | B7: DHL | C7: 2024/05/21 | D7: 45433 | E7: 9317.41 | F7: On Time
A8: SHP7 | B8: FedEx | C8: 2026/01/10 | D8: 46032 | E8: 5961.25 | F8: Lost
A9: SHP8 | B9: FedEx | C9: 2025/08/24 | D9: 45893 | E9: 7591.38 | F9: Lost
A10: SHP9 | B10: DHL | C10: 2024/04/17 | D10: 45399 | E10: 3753.9 | F10: On Time
A11: SHP10 | B11: UPS | C11: 2025/09/28 | D11: 45928 | E11: 3558.83 | F11: Delayed
A12: SHP11 | B12: TCS | C12: 2025/03/12 | D12: 45728 | E12: 878.39 | F12: Lost
A13: SHP12 | B13: DHL | C13: 2026/01/10 | D13: 46032 | E13: 6317.87 | F13: Delayed
A14: SHP13 | B14: DHL | C14: 2024/08/31 | D14: 45535 | E14: 477.41 | F14: Lost
A15: SHP14 | B15: DHL | C15: 2024/01/07 | D15: 45298 | E15: 8657.88 | F15: Delayed
... A2001: SHP2000 | B2001: DHL | C2001: 2025/09/09 | D2001: 45909 | E2001: 1932.71 | F2001: Lost

Sheet Returns
A1: Return_ID | B1: Order_ID | C1: Reason | D1: Refund_Amount | E1: Return_Date | F1: Clean_Return_Date
A2: RET1 | B2: ORD5988 | C2: Damaged | D2: 868.39 | E2: 03/18/2026 | F2: 46099 | H2: Damaged Returns | I2: =COUNTIF(Returns!C:C, "Damaged") -> 144
A3: RET2 | B3: ORD2836 | C3: Wrong Item | D3: 944.25 | E3: 05/14/2024 | F3: 45426
A4: RET3 | B4: ORD4079 | C4: Late Delivery | D4: 433.62 | E4: 08/03/2025 | F4: 45872
A5: RET4 | B5: ORD4851 | C5: Customer Changed Mind | D5: 552.58 | E5: 03/13/2024 | F5: 45364
A6: RET5 | B6: ORD2110 | C6: Customer Changed Mind | D6: 415.1 | E6: 11/30/2025 | F6: 45991
A7: RET6 | B7: ORD5753 | C7: Damaged | D7: 397.33 | E7: 08/10/2025 | F7: 45879
A8: RET7 | B8: ORD5641 | C8: Wrong Item | D8: 734.13 | E8: 04/13/2025 | F8: 45760
A9: RET8 | B9: ORD4711 | C9: Damaged | D9: 681.57 | E9: 05/29/2025 | F9: 45806
A10: RET9 | B10: ORD4476 | C10: Customer Changed Mind | D10: 367.99 | E10: 03/21/2026 | F10: 46102
A11: RET10 | B11: ORD3428 | C11: Customer Changed Mind | D11: 383.73 | E11: 09/03/2025 | F11: 45903
A12: RET11 | B12: ORD4685 | C12: Customer Changed Mind | D12: 670.34 | E12: 11/23/2024 | F12: 45619
A13: RET12 | B13: ORD5918 | C13: Customer Changed Mind | D13: 500.63 | E13: 05/08/2025 | F13: 45785
A14: RET13 | B14: ORD2752 | C14: Damaged | D14: 58.45 | E14: 04/18/2025 | F14: 45765
... A601: RET600 | B601: ORD2229 | C601: Wrong Item | D601: 485.25 | E601: 09/21/2024 | F601: 45556
